Workbook
Name Slicer_DayName: #N/A
Name Slicer_Month: #N/A
Name Slicer_Movie_Type: #N/A
Name Slicer_Profit___Loss: #N/A
Name Slicer_Runtime_Classification: #N/A
Name Slicer_Vote_Category: #N/A
Name Slicer_year1: #N/A

Sheet imdb_data
A1: id | B1: primaryTitle | C1: originalTitle | D1: isAdult | E1: runtimeMinutes | F1: Hour | G1: Minutes | H1: Runtime Classification | I1: Genres1 | J1: Genres2 | K1: Genres3 | L1: averageRating | M1: Movie Type | N1: numVotes | O1: Vote Category | P1: budget | Q1: gross | R1: Profit | S1: Profit & Loss | T1: release_date | U1: directors | V1: Release_Date | W1: Month | X1: Year | Y1: year1 | Z1: Day | AA1: day 1 | AB1: DayName
A2: tt0035423 | B2: Kate & Leopold | C2: Kate & Leopold | D2: 0 | E2: 118 | F2: =INT(E2/60) -> 1 | G2: =MOD(E2,60) -> 58 | H2: {=_xlfn.IFS(E2<=80,"Series",E2<=120,"TV Movie",E2>120,"Long Movie")} -> TV Movie | I2: Comedy | J2: Fantasy | K2: Romance | L2: 6.4 | M2: {=_xlfn.IFS(L2<=2,"Flop",L2<=5,"Average",L2<=7,"Hit",L2<=9,"Superhit",L2>9,"BlockBuster")} -> Hit | N2: 87925 | O2: {=_xlfn.IFS(N2<=100000,"Low",N2<=500000,"Median",N2<=1500000,"High",N2>1500000,"Very High")} -> Low | P2: 48000000 | Q2: 76019048 | R2: =Q2-P2 -> 28019048 | S2: =IF(R2>0,"Profit","Loss") -> Profit | T2: 37236 | U2: James Mangold | V2: 37236 | W2: =TEXT(V2,"MMMM") -> December | X2: =TEXT(V2,"YYYY") -> 2001 | Y2: =VALUE(X2) -> 2001 | Z2: =TEXT(V2,"d") -> 11 | AA2: =VALUE(Z2) -> 11 | AB2: =TEXT(V2,"dddd") -> Tuesday
A3: tt0065421 | B3: The Aristocats | C3: The AristoCats | D3: 0 | E3: 78 | F3: =INT(E3/60) -> 1 | G3: =MOD(E3,60) -> 18 | H3: {=_xlfn.IFS(E3<=80,"Series",E3<=120,"TV Movie",E3>120,"Long Movie")} -> Series | I3: Adventure | J3: Animation | K3: Comedy | L3: 7.1 | M3: {=_xlfn.IFS(L3<=2,"Flop",L3<=5,"Average",L3<=7,"Hit",L3<=9,"Superhit",L3>9,"BlockBuster")} -> Superhit | N3: 111758 | O3: {=_xlfn.IFS(N3<=100000,"Low",N3<=500000,"Median",N3<=1500000,"High",N3>1500000,"Very High")} -> Median | P3: 4000000 | Q3: 35459543 | R3: =Q3-P3 -> 31459543 | S3: =IF(R3>0,"Profit","Loss") -> Profit | T3: 25913 | U3: Wolfgang Reitherman | V3: 25913 | W3: =TEXT(V3,"MMMM") -> December | X3: =TEXT(V3,"YYYY") -> 1970 | Y3: =VALUE(X3) -> 1970 | Z3: =TEXT(V3,"d") -> 11 | AA3: =VALUE(Z3) -> 11 | AB3: =TEXT(V3,"dddd") -> Friday
A4: tt0065938 | B4: Kelly's Heroes | C4: Kelly's Heroes | D4: 0 | E4: 144 | F4: =INT(E4/60) -> 2 | G4: =MOD(E4,60) -> 24 | H4: {=_xlfn.IFS(E4<=80,"Series",E4<=120,"TV Movie",E4>120,"Long Movie")} -> Long Movie | I4: Adventure | J4: Comedy | K4: War | L4: 7.6 | M4: {=_xlfn.IFS(L4<=2,"Flop",L4<=5,"Average",L4<=7,"Hit",L4<=9,"Superhit",L4>9,"BlockBuster")} -> Superhit | N4: 52628 | O4: {=_xlfn.IFS(N4<=100000,"Low",N4<=500000,"Median",N4<=1500000,"High",N4>1500000,"Very High")} -> Low | P4: 4000000 | Q4: 5200000 | R4: =Q4-P4 -> 1200000 | S4: =IF(R4>0,"Profit","Loss") -> Profit | T4: 25569 | U4: Brian G. Hutton | V4: 25569 | W4: =TEXT(V4,"MMMM") -> January | X4: =TEXT(V4,"YYYY") -> 1970 | Y4: =VALUE(X4) -> 1970 | Z4: =TEXT(V4,"d") -> 1 | AA4: =VALUE(Z4) -> 1 | AB4: =TEXT(V4,"dddd") -> Thursday
A5: tt0066026 | B5: M*A*S*H | C5: M*A*S*H | D5: 0 | E5: 116 | F5: =INT(E5/60) -> 1 | G5: =MOD(E5,60) -> 56 | H5: {=_xlfn.IFS(E5<=80,"Series",E5<=120,"TV Movie",E5>120,"Long Movie")} -> TV Movie | I5: Comedy | J5: Drama | K5: War | L5: 7.4 | M5: {=_xlfn.IFS(L5<=2,"Flop",L5<=5,"Average",L5<=7,"Hit",L5<=9,"Superhit",L5>9,"BlockBuster")} -> Superhit | N5: 75784 | O5: {=_xlfn.IFS(N5<=100000,"Low",N5<=500000,"Median",N5<=1500000,"High",N5>1500000,"Very High")} -> Low | P5: 3500000 | Q5: 81600000 | R5: =Q5-P5 -> 78100000 | S5: =IF(R5>0,"Profit","Loss") -> Profit | T5: 25593 | U5: Robert Altman | V5: 25593 | W5: =TEXT(V5,"MMMM") -> January | X5: =TEXT(V5,"YYYY") -> 1970 | Y5: =VALUE(X5) -> 1970 | Z5: =TEXT(V5,"d") -> 25 | AA5: =VALUE(Z5) -> 25 | AB5: =TEXT(V5,"dddd") -> Sunday
A6: tt0066206 | B6: Patton | C6: Patton | D6: 0 | E6: 172 | F6: =INT(E6/60) -> 2 | G6: =MOD(E6,60) -> 52 | H6: {=_xlfn.IFS(E6<=80,"Series",E6<=120,"TV Movie",E6>120,"Long Movie")} -> Long Movie | I6: Biography | J6: Drama | K6: War | L6: 7.9 | M6: {=_xlfn.IFS(L6<=2,"Flop",L6<=5,"Average",L6<=7,"Hit",L6<=9,"Superhit",L6>9,"BlockBuster")} -> Superhit | N6: 106476 | O6: {=_xlfn.IFS(N6<=100000,"Low",N6<=500000,"Median",N6<=1500000,"High",N6>1500000,"Very High")} -> Median | P6: 12000000 | Q6: 61749765 | R6: =Q6-P6 -> 49749765 | S6: =IF(R6>0,"Profit","Loss") -> Profit | T6: 25603 | U6: Franklin J. Schaffner | V6: 25603 | W6: =TEXT(V6,"MMMM") -> February | X6: =TEXT(V6,"YYYY") -> 1970 | Y6: =VALUE(X6) -> 1970 | Z6: =TEXT(V6,"d") -> 4 | AA6: =VALUE(Z6) -> 4 | AB6: =TEXT(V6,"dddd") -> Wednesday
A7: tt0066434 | B7: THX 1138 | C7: THX 1138 | D7: 0 | E7: 86 | F7: =INT(E7/60) -> 1 | G7: =MOD(E7,60) -> 26 | H7: {=_xlfn.IFS(E7<=80,"Series",E7<=120,"TV Movie",E7>120,"Long Movie")} -> TV Movie | I7: Drama | J7: Sci-Fi | K7: Thriller | L7: 6.6 | M7: {=_xlfn.IFS(L7<=2,"Flop",L7<=5,"Average",L7<=7,"Hit",L7<=9,"Superhit",L7>9,"BlockBuster")} -> Hit | N7: 53906 | O7: {=_xlfn.IFS(N7<=100000,"Low",N7<=500000,"Median",N7<=1500000,"High",N7>1500000,"Very High")} -> Low | P7: 777000 | Q7: 2437000 | R7: =Q7-P7 -> 1660000 | S7: =IF(R7>0,"Profit","Loss") -> Profit | T7: 26003 | U7: George Lucas | V7: 26003 | W7: =TEXT(V7,"MMMM") -> March | X7: =TEXT(V7,"YYYY") -> 1971 | Y7: =VALUE(X7) -> 1971 | Z7: =TEXT(V7,"d") -> 11 | AA7: =VALUE(Z7) -> 11 | AB7: =TEXT(V7,"dddd") -> Thursday
A8: tt0066921 | B8: A Clockwork Orange | C8: A Clockwork Orange | D8: 0 | E8: 136 | F8: =INT(E8/60) -> 2 | G8: =MOD(E8,60) -> 16 | H8: {=_xlfn.IFS(E8<=80,"Series",E8<=120,"TV Movie",E8>120,"Long Movie")} -> Long Movie | I8: Crime | J8: Sci-Fi | K8: Unknown | L8: 8.3 | M8: {=_xlfn.IFS(L8<=2,"Flop",L8<=5,"Average",L8<=7,"Hit",L8<=9,"Superhit",L8>9,"BlockBuster")} -> Superhit | N8: 864440 | O8: {=_xlfn.IFS(N8<=100000,"Low",N8<=500000,"Median",N8<=1500000,"High",N8>1500000,"Very High")} -> High | P8: 2200000 | Q8: 26960374 | R8: =Q8-P8 -> 24760374 | S8: =IF(R8>0,"Profit","Loss") -> Profit | T8: 26286 | U8: Stanley Kubrick | V8: 26286 | W8: =TEXT(V8,"MMMM") -> December | X8: =TEXT(V8,"YYYY") -> 1971 | Y8: =VALUE(X8) -> 1971 | Z8: =TEXT(V8,"d") -> 19 | AA8: =VALUE(Z8) -> 19 | AB8: =TEXT(V8,"dddd") -> Sunday
A9: tt0066995 | B9: Diamonds Are Forever | C9: Diamonds Are Forever | D9: 0 | E9: 120 | F9: =INT(E9/60) -> 2 | G9: =MOD(E9,60) -> 0 | H9: {=_xlfn.IFS(E9<=80,"Series",E9<=120,"TV Movie",E9>120,"Long Movie")} -> TV Movie | I9: Action | J9: Adventure | K9: Thriller | L9: 6.5 | M9: {=_xlfn.IFS(L9<=2,"Flop",L9<=5,"Average",L9<=7,"Hit",L9<=9,"Superhit",L9>9,"BlockBuster")} -> Hit | N9: 112043 | O9: {=_xlfn.IFS(N9<=100000,"Low",N9<=500000,"Median",N9<=1500000,"High",N9>1500000,"Very High")} -> Median | P9: 7200000 | Q9: 43829933 | R9: =Q9-P9 -> 36629933 | S9: =IF(R9>0,"Profit","Loss") -> Profit | T9: 26281 | U9: Guy Hamilton | V9: 26281 | W9: =TEXT(V9,"MMMM") -> December | X9: =TEXT(V9,"YYYY") -> 1971 | Y9: =VALUE(X9) -> 1971 | Z9: =TEXT(V9,"d") -> 14 | AA9: =VALUE(Z9) -> 14 | AB9: =TEXT(V9,"dddd") -> Tuesday
A10: tt0066999 | B10: Dirty Harry | C10: Dirty Harry | D10: 0 | E10: 102 | F10: =INT(E10/60) -> 1 | G10: =MOD(E10,60) -> 42 | H10: {=_xlfn.IFS(E10<=80,"Series",E10<=120,"TV Movie",E10>120,"Long Movie")} -> TV Movie | I10: Action | J10: Crime | K10: Thriller | L10: 7.7 | M10: {=_xlfn.IFS(L10<=2,"Flop",L10<=5,"Average",L10<=7,"Hit",L10<=9,"Superhit",L10>9,"BlockBuster")} -> Superhit | N10: 165277 | O10: {=_xlfn.IFS(N10<=100000,"Low",N10<=500000,"Median",N10<=1500000,"High",N10>1500000,"Very High")} -> Median | P10: 4000000 | Q10: 35988495 | R10: =Q10-P10 -> 31988495 | S10: =IF(R10>0,"Profit","Loss") -> Profit | T10: 26288 | U10: Don Siegel, Clint Eastwood | V10: 26288 | W10: =TEXT(V10,"MMMM") -> December | X10: =TEXT(V10,"YYYY") -> 1971 | Y10: =VALUE(X10) -> 1971 | Z10: =TEXT(V10,"d") -> 21 | AA10: =VALUE(Z10) -> 21 | AB10: =TEXT(V10,"dddd") -> Tuesday
A11: tt0067116 | B11: The French Connection | C11: The French Connection | D11: 0 | E11: 104 | F11: =INT(E11/60) -> 1 | G11: =MOD(E11,60) -> 44 | H11: {=_xlfn.IFS(E11<=80,"Series",E11<=120,"TV Movie",E11>120,"Long Movie")} -> TV Movie | I11: Action | J11: Crime | K11: Drama | L11: 7.7 | M11: {=_xlfn.IFS(L11<=2,"Flop",L11<=5,"Average",L11<=7,"Hit",L11<=9,"Superhit",L11>9,"BlockBuster")} -> Superhit | N11: 131995 | O11: {=_xlfn.IFS(N11<=100000,"Low",N11<=500000,"Median",N11<=1500000,"High",N11>1500000,"Very High")} -> Median | P11: 1800000 | Q11: 51701871 | R11: =Q11-P11 -> 49901871 | S11: =IF(R11>0,"Profit","Loss") -> Profit | T11: 26213 | U11: William Friedkin | V11: 26213 | W11: =TEXT(V11,"MMMM") -> October | X11: =TEXT(V11,"YYYY") -> 1971 | Y11: =VALUE(X11) -> 1971 | Z11: =TEXT(V11,"d") -> 7 | AA11: =VALUE(Z11) -> 7 | AB11: =TEXT(V11,"dddd") -> Thursday
A12: tt0067185 | B12: Harold and Maude | C12: Harold and Maude | D12: 0 | E12: 91 | F12: =INT(E12/60) -> 1 | G12: =MOD(E12,60) -> 31 | H12: {=_xlfn.IFS(E12<=80,"Series",E12<=120,"TV Movie",E12>120,"Long Movie")} -> TV Movie | I12: Comedy | J12: Drama | K12: Romance | L12: 7.9 | M12: {=_xlfn.IFS(L12<=2,"Flop",L12<=5,"Average",L12<=7,"Hit",L12<=9,"Superhit",L12>9,"BlockBuster")} -> Superhit | N12: 80626 | O12: {=_xlfn.IFS(N12<=100000,"Low",N12<=500000,"Median",N12<=1500000,"High",N12>1500000,"Very High")} -> Low | P12: 1200000 | Q12: 1546 | R12: =Q12-P12 -> -1198454 | S12: =IF(R12>0,"Profit","Loss") -> Loss | T12: 26287 | U12: Hal Ashby | V12: 26287 | W12: =TEXT(V12,"MMMM") -> December | X12: =TEXT(V12,"YYYY") -> 1971 | Y12: =VALUE(X12) -> 1971 | Z12: =TEXT(V12,"d") -> 20 | AA12: =VALUE(Z12) -> 20 | AB12: =TEXT(V12,"dddd") -> Monday
A13: tt0067328 | B13: The Last Picture Show | C13: The Last Picture Show | D13: 0 | E13: 118 | F13: =INT(E13/60) -> 1 | G13: =MOD(E13,60) -> 58 | H13: {=_xlfn.IFS(E13<=80,"Series",E13<=120,"TV Movie",E13>120,"Long Movie")} -> TV Movie | I13: Drama | J13: Romance | K13: Unknown | L13: 8 | M13: {=_xlfn.IFS(L13<=2,"Flop",L13<=5,"Average",L13<=7,"Hit",L13<=9,"Superhit",L13>9,"BlockBuster")} -> Superhit | N13: 51275 | O13: {=_xlfn.IFS(N13<=100000,"Low",N13<=500000,"Median",N13<=1500000,"High",N13>1500000,"Very High")} -> Low | P13: 1300000 | Q13: 29146131 | R13: =Q13-P13 -> 27846131 | S13: =IF(R13>0,"Profit","Loss") -> Profit | T13: 26208 | U13: Peter Bogdanovich | V13: 26208 | W13: =TEXT(V13,"MMMM") -> October | X13: =TEXT(V13,"YYYY") -> 1971 | Y13: =VALUE(X13) -> 1971 | Z13: =TEXT(V13,"d") -> 2 | AA13: =VALUE(Z13) -> 2 | AB13: =TEXT(V13,"dddd") -> Saturday
... A466: tt0106977 | B466: The Fugitive | C466: The Fugitive | D466: 0 | E466: 130 | F466: =INT(E466/60) -> 2 | G466: =MOD(E466,60) -> 10 | H466: {=_xlfn.IFS(E466<=80,"Series",E466<=120,"TV Movie",E466>120,"Long Movie")} -> Long Movie | I466: Action | J466: Crime | K466: Drama | L466: 7.8 | M466: {=_xlfn.IFS(L466<=2,"Flop",L466<=5,"Average",L466<=7,"Hit",L466<=9,"Superhit",L466>9,"BlockBuster")} -> Superhit | N466: 310966 | O466: {=_xlfn.IFS(N466<=100000,"Low",N466<=500000,"Median",N466<=1500000,"High",N466>1500000,"Very High")} -> Median | P466: 44000000 | Q466: 368875760 | R466: =Q466-P466 -> 324875760 | S466: =IF(R466>0,"Profit","Loss") -> Profit | T466: 34179 | U466: Andrew Davis | V466: 34179 | W466: =TEXT(V466,"MMMM") -> July | X466: =TEXT(V466,"YYYY") -> 1993 | Y466: =VALUE(X466) -> 1993 | Z466: =TEXT(V466,"d") -> 29 | AA466: =VALUE(Z466) -> 29 | AB466: =TEXT(V466,"dddd") -> Thursday
A467: tt0107048 | B467: Groundhog Day | C467: Groundhog Day | D467: 0 | E467: 101 | F467: =INT(E467/60) -> 1 | G467: =MOD(E467,60) -> 41 | H467: {=_xlfn.IFS(E467<=80,"Series",E467<=120,"TV Movie",E467>120,"Long Movie")} -> TV Movie | I467: Comedy | J467: Drama | K467: Fantasy | L467: 8 | M467: {=_xlfn.IFS(L467<=2,"Flop",L467<=5,"Average",L467<=7,"Hit",L467<=9,"Superhit",L467>9,"BlockBuster")} -> Superhit | N467: 666512 | O467: {=_xlfn.IFS(N467<=100000,"Low",N467<=500000,"Median",N467<=1500000,"High",N467>1500000,"Very High")} -> High | P467: 14600000 | Q467: 71108591 | R467: =Q467-P467 -> 56508591 | S467: =IF(R467>0,"Profit","Loss") -> Profit | T467: NA | U467: Harold Ramis | V467: NA | W467: =TEXT(V467,"MMMM") -> NA | X467: =TEXT(V467,"YYYY") -> NA | Y467: =VALUE(X467) -> #VALUE! | Z467: =TEXT(V467,"d") -> NA | AA467: =VALUE(Z467) -> #VALUE! | AB467: =TEXT(V467,"dddd") -> NA
A468: tt0107076 | B468: Hard Target | C468: Hard Target | D468: 0 | E468: 97 | F468: =INT(E468/60) -> 1 | G468: =MOD(E468,60) -> 37 | H468: {=_xlfn.IFS(E468<=80,"Series",E468<=120,"TV Movie",E468>120,"Long Movie")} -> TV Movie | I468: Action | J468: Crime | K468: Thriller | L468: 6.2 | M468: {=_xlfn.IFS(L468<=2,"Flop",L468<=5,"Average",L468<=7,"Hit",L468<=9,"Superhit",L468>9,"BlockBuster")} -> Hit | N468: 54931 | O468: {=_xlfn.IFS(N468<=100000,"Low",N468<=500000,"Median",N468<=1500000,"High",N468>1500000,"Very High")} -> Low | P468: 18000000 | Q468: 74189677 | R468: =Q468-P468 -> 56189677 | S468: =IF(R468>0,"Profit","Loss") -> Profit | T468: 34201 | U468: John Woo | V468: 34201 | W468: =TEXT(V468,"MMMM") -> August | X468: =TEXT(V468,"YYYY") -> 1993 | Y468: =VALUE(X468) -> 1993 | Z468: =TEXT(V468,"d") -> 20 | AA468: =VALUE(Z468) -> 20 | AB468: =TEXT(V468,"dddd") -> Friday
A469: tt0107120 | B469: Hocus Pocus | C469: Hocus Pocus | D469: 0 | E469: 96 | F469: =INT(E469/60) -> 1 | G469: =MOD(E469,60) -> 36 | H469: {=_xlfn.IFS(E469<=80,"Series",E469<=120,"TV Movie",E469>120,"Long Movie")} -> TV Movie | I469: Comedy | J469: Family | K469: Fantasy | L469: 6.9 | M469: {=_xlfn.IFS(L469<=2,"Flop",L469<=5,"Average",L469<=7,"Hit",L469<=9,"Superhit",L469>9,"BlockBuster")} -> Hit | N469: 153494 | O469: {=_xlfn.IFS(N469<=100000,"Low",N469<=500000,"Median",N469<=1500000,"High",N469>1500000,"Very High")} -> Median | P469: 28000000 | Q469: 50789441 | R469: =Q469-P469 -> 22789441 | S469: =IF(R469>0,"Profit","Loss") -> Profit | T469: 34160 | U469: Kenny Ortega | V469: 34160 | W469: =TEXT(V469,"MMMM") -> July | X469: =TEXT(V469,"YYYY") -> 1993 | Y469: =VALUE(X469) -> 1993 | Z469: =TEXT(V469,"d") -> 10 | AA469: =VALUE(Z469) -> 10 | AB469: =TEXT(V469,"dddd") -> Saturday
A470: tt0107144 | B470: Hot Shots! Part Deux | C470: Hot Shots! Part Deux | D470: 0 | E470: 86 | F470: =INT(E470/60) -> 1 | G470: =MOD(E470,60) -> 26 | H470: {=_xlfn.IFS(E470<=80,"Series",E470<=120,"TV Movie",E470>120,"Long Movie")} -> TV Movie | I470: Action | J470: Comedy | K470: Unknown | L470: 6.6 | M470: {=_xlfn.IFS(L470<=2,"Flop",L470<=5,"Average",L470<=7,"Hit",L470<=9,"Superhit",L470>9,"BlockBuster")} -> Hit | N470: 95577 | O470: {=_xlfn.IFS(N470<=100000,"Low",N470<=500000,"Median",N470<=1500000,"High",N470>1500000,"Very High")} -> Low | P470: 25000000 | Q470: 133752825 | R470: =Q470-P470 -> 108752825 | S470: =IF(R470>0,"Profit","Loss") -> Profit | T470: 34110 | U470: Jim Abrahams | V470: 34110 | W470: =TEXT(V470,"MMMM") -> May | X470: =TEXT(V470,"YYYY") -> 1993 | Y470: =VALUE(X470) -> 1993 | Z470: =TEXT(V470,"d") -> 21 | AA470: =VALUE(Z470) -> 21 | AB470: =TEXT(V470,"dddd") -> Friday
A471: tt0107206 | B471: In the Line of Fire | C471: In the Line of Fire | D471: 0 | E471: 128 | F471: =INT(E471/60) -> 2 | G471: =MOD(E471,60) -> 8 | H471: {=_xlfn.IFS(E471<=80,"Series",E471<=120,"TV Movie",E471>120,"Long Movie")} -> Long Movie | I471: Action | J471: Crime | K471: Drama | L471: 7.2 | M471: {=_xlfn.IFS(L471<=2,"Flop",L471<=5,"Average",L471<=7,"Hit",L471<=9,"Superhit",L471>9,"BlockBuster")} -> Superhit | N471: 111126 | O471: {=_xlfn.IFS(N471<=100000,"Low",N471<=500000,"Median",N471<=1500000,"High",N471>1500000,"Very High")} -> Median | P471: 40000000 | Q471: 176997168 | R471: =Q471-P471 -> 136997168 | S471: =IF(R471>0,"Profit","Loss") -> Profit | T471: 34158 | U471: Wolfgang Petersen | V471: 34158 | W471: =TEXT(V471,"MMMM") -> July | X471: =TEXT(V471,"YYYY") -> 1993 | Y471: =VALUE(X471) -> 1993 | Z471: =TEXT(V471,"d") -> 8 | AA471: =VALUE(Z471) -> 8 | AB471: =TEXT(V471,"dddd") -> Thursday
A472: tt0107207 | B472: In the Name of the Father | C472: In the Name of the Father | D472: 0 | E472: 133 | F472: =INT(E472/60) -> 2 | G472: =MOD(E472,60) -> 13 | H472: {=_xlfn.IFS(E472<=80,"Series",E472<=120,"TV Movie",E472>120,"Long Movie")} -> Long Movie | I472: Biography | J472: Crime | K472: Drama | L472: 8.1 | M472: {=_xlfn.IFS(L472<=2,"Flop",L472<=5,"Average",L472<=7,"Hit",L472<=9,"Superhit",L472>9,"BlockBuster")} -> Superhit | N472: 183546 | O472: {=_xlfn.IFS(N472<=100000,"Low",N472<=500000,"Median",N472<=1500000,"High",N472>1500000,"Very High")} -> Median | P472: 13000000 | Q472: 65796862 | R472: =Q472-P472 -> 52796862 | S472: =IF(R472>0,"Profit","Loss") -> Profit | T472: 34315 | U472: Jim Sheridan | V472: 34315 | W472: =TEXT(V472,"MMMM") -> December | X472: =TEXT(V472,"YYYY") -> 1993 | Y472: =VALUE(X472) -> 1993 | Z472: =TEXT(V472,"d") -> 12 | AA472: =VALUE(Z472) -> 12 | AB472: =TEXT(V472,"dddd") -> Sunday
A473: tt0107211 | B473: Indecent Proposal | C473: Indecent Proposal | D473: 0 | E473: 117 | F473: =INT(E473/60) -> 1 | G473: =MOD(E473,60) -> 57 | H473: {=_xlfn.IFS(E473<=80,"Series",E473<=120,"TV Movie",E473>120,"Long Movie")} -> TV Movie | I473: Drama | J473: Romance | K473: Unknown | L473: 6 | M473: {=_xlfn.IFS(L473<=2,"Flop",L473<=5,"Average",L473<=7,"Hit",L473<=9,"Superhit",L473>9,"BlockBuster")} -> Hit | N473: 76245 | O473: {=_xlfn.IFS(N473<=100000,"Low",N473<=500000,"Median",N473<=1500000,"High",N473>1500000,"Very High")} -> Low | P473: 38000000 | Q473: 266614059 | R473: =Q473-P473 -> 228614059 | S473: =IF(R473>0,"Profit","Loss") -> Profit | T473: 34065 | U473: Adrian Lyne | V473: 34065 | W473: =TEXT(V473,"MMMM") -> April | X473: =TEXT(V473,"YYYY") -> 1993 | Y473: =VALUE(X473) -> 1993 | Z473: =TEXT(V473,"d") -> 6 | AA473: =VALUE(Z473) -> 6 | AB473: =TEXT(V473,"dddd") -> Tuesday
A474: tt0107290 | B474: Jurassic Park | C474: Jurassic Park | D474: 0 | E474: 127 | F474: =INT(E474/60) -> 2 | G474: =MOD(E474,60) -> 7 | H474: {=_xlfn.IFS(E474<=80,"Series",E474<=120,"TV Movie",E474>120,"Long Movie")} -> Long Movie | I474: Action | J474: Adventure | K474: Sci-Fi | L474: 8.2 | M474: {=_xlfn.IFS(L474<=2,"Flop",L474<=5,"Average",L474<=7,"Hit",L474<=9,"Superhit",L474>9,"BlockBuster")} -> Superhit | N474: 1041089 | O474: {=_xlfn.IFS(N474<=100000,"Low",N474<=500000,"Median",N474<=1500000,"High",N474>1500000,"Very High")} -> High | P474: 63000000 | Q474: 1113138548 | R474: =Q474-P474 -> 1050138548 | S474: =IF(R474>0,"Profit","Loss") -> Profit | T474: 34129 | U474: Steven Spielberg | V474: 34129 | W474: =TEXT(V474,"MMMM") -> June | X474: =TEXT(V474,"YYYY") -> 1993 | Y474: =VALUE(X474) -> 1993 | Z474: =TEXT(V474,"d") -> 9 | AA474: =VALUE(Z474) -> 9 | AB474: =TEXT(V474,"dddd") -> Wednesday
A475: tt0107302 | B475: Kalifornia | C475: Kalifornia | D475: 0 | E475: 117 | F475: =INT(E475/60) -> 1 | G475: =MOD(E475,60) -> 57 | H475: {=_xlfn.IFS(E475<=80,"Series",E475<=120,"TV Movie",E475>120,"Long Movie")} -> TV Movie | I475: Crime | J475: Drama | K475: Thriller | L475: 6.7 | M475: {=_xlfn.IFS(L475<=2,"Flop",L475<=5,"Average",L475<=7,"Hit",L475<=9,"Superhit",L475>9,"BlockBuster")} -> Hit | N475: 56797 | O475: {=_xlfn.IFS(N475<=100000,"Low",N475<=500000,"Median",N475<=1500000,"High",N475>1500000,"Very High")} -> Low | P475: 9000000 | Q475: 2395231 | R475: =Q475-P475 -> -6604769 | S475: =IF(R475>0,"Profit","Loss") -> Loss | T475: 34182 | U475: Dominic Sena | V475: 34182 | W475: =TEXT(V475,"MMMM") -> August | X475: =TEXT(V475,"YYYY") -> 1993 | Y475: =VALUE(X475) -> 1993 | Z475: =TEXT(V475,"d") -> 1 | AA475: =VALUE(Z475) -> 1 | AB475: =TEXT(V475,"dddd") -> Sunday
A476: tt0107362 | B476: Last Action Hero | C476: Last Action Hero | D476: 0 | E476: 130 | F476: =INT(E476/60) -> 2 | G476: =MOD(E476,60) -> 10 | H476: {=_xlfn.IFS(E476<=80,"Series",E476<=120,"TV Movie",E476>120,"Long Movie")} -> Long Movie | I476: Action | J476: Adventure | K476: Comedy | L476: 6.5 | M476: {=_xlfn.IFS(L476<=2,"Flop",L476<=5,"Average",L476<=7,"Hit",L476<=9,"Superhit",L476>9,"BlockBuster")} -> Hit | N476: 160479 | O476: {=_xlfn.IFS(N476<=100000,"Low",N476<=500000,"Median",N476<=1500000,"High",N476>1500000,"Very High")} -> Median | P476: 85000000 | Q476: 137298489 | R476: =Q476-P476 -> 52298489 | S476: =IF(R476>0,"Profit","Loss") -> Profit | T476: 34133 | U476: John McTiernan | V476: 34133 | W476: =TEXT(V476,"MMMM") -> June | X476: =TEXT(V476,"YYYY") -> 1993 | Y476: =VALUE(X476) -> 1993 | Z476: =TEXT(V476,"d") -> 13 | AA476: =VALUE(Z476) -> 13 | AB476: =TEXT(V476,"dddd") -> Sunday
A477: tt0107554 | B477: Menace II Society | C477: Menace II Society | D477: 0 | E477: 97 | F477: =INT(E477/60) -> 1 | G477: =MOD(E477,60) -> 37 | H477: {=_xlfn.IFS(E477<=80,"Series",E477<=120,"TV Movie",E477>120,"Long Movie")} -> TV Movie | I477: Crime | J477: Drama | K477: Thriller | L477: 7.5 | M477: {=_xlfn.IFS(L477<=2,"Flop",L477<=5,"Average",L477<=7,"Hit",L477<=9,"Superhit",L477>9,"BlockBuster")} -> Superhit | N477: 63036 | O477: {=_xlfn.IFS(N477<=100000,"Low",N477<=500000,"Median",N477<=1500000,"High",N477>1500000,"Very High")} -> Low | P477: 3500000 | Q477: 27912072 | R477: =Q477-P477 -> 24412072 | S477: =IF(R477>0,"Profit","Loss") -> Profit | T477: 34115 | U477: Albert Hughes, Allen Hughes | V477: 34115 | W477: =TEXT(V477,"MMMM") -> May | X477: =TEXT(V477,"YYYY") -> 1993 | Y477: =VALUE(X477) -> 1993 | Z477: =TEXT(V477,"d") -> 26 | AA477: =VALUE(Z477) -> 26 | AB477: =TEXT(V477,"dddd") -> Wednesday
A478: tt0107614 | B478: Mrs. Doubtfire | C478: Mrs. Doubtfire | D478: 0 | E478: 125 | F478: =INT(E478/60) -> 2 | G478: =MOD(E478,60) -> 5 | H478: {=_xlfn.IFS(E478<=80,"Series",E478<=120,"TV Movie",E478>120,"Long Movie")} -> Long Movie | I478: Comedy | J478: Drama | K478: Unknown | L478: 7.1 | M478: {=_xlfn.IFS(L478<=2,"Flop",L478<=5,"Average",L478<=7,"Hit",L478<=9,"Superhit",L478>9,"BlockBuster")} -> Superhit | N478: 283743 | O478: {=_xlfn.IFS(N478<=100000,"Low",N478<=500000,"Median",N478<=1500000,"High",N478>1500000,"Very High")} -> Median | P478: 25000000 | Q478: 441286195 | R478: =Q478-P478 -> 416286195 | S478: =IF(R478>0,"Profit","Loss") -> Profit | T478: 34295 | U478: Chris Columbus | V478: 34295 | W478: =TEXT(V478,"MMMM") -> November | X478: =TEXT(V478,"YYYY") -> 1993 | Y478: =VALUE(X478) -> 1993 | Z478: =TEXT(V478,"d") -> 22 | AA478: =VALUE(Z478) -> 22 | AB478: =TEXT(V478,"dddd") -> Monday
A479: tt0107616 | B479: Much Ado About Nothing | C479: Much Ado About Nothing | D479: 0 | E479: 111 | F479: =INT(E479/60) -> 1 | G479: =MOD(E479,60) -> 51 | H479: {=_xlfn.IFS(E479<=80,"Series",E479<=120,"TV Movie",E479>120,"Long Movie")} -> TV Movie | I479: Comedy | J479: Drama | K479: Romance | L479: 7.3 | M479: {=_xlfn.IFS(L479<=2,"Flop",L479<=5,"Average",L479<=7,"Hit",L479<=9,"Superhit",L479>9,"BlockBuster")} -> Superhit | N479: 50854 | O479: {=_xlfn.IFS(N479<=100000,"Low",N479<=500000,"Median",N479<=1500000,"High",N479>1500000,"Very High")} -> Low | P479: 11000000 | Q479: 22549338 | R479: =Q479-P479 -> 11549338 | S479: =IF(R479>0,"Profit","Loss") -> Profit | T479: 34095 | U479: Kenneth Branagh | V479: 34095 | W479: =TEXT(V479,"MMMM") -> May | X479: =TEXT(V479,"YYYY") -> 1993 | Y479: =VALUE(X479) -> 1993 | Z479: =TEXT(V479,"d") -> 6 | AA479: =VALUE(Z479) -> 6 | AB479: =TEXT(V479,"dddd") -> Thursday
... A525: tt0110912 | B525: Pulp Fiction | C525: Pulp Fiction | D525: 0 | E525: 154 | F525: =INT(E525/60) -> 2 | G525: =MOD(E525,60) -> 34 | H525: {=_xlfn.IFS(E525<=80,"Series",E525<=120,"TV Movie",E525>120,"Long Movie")} -> Long Movie | I525: Crime | J525: Drama | K525: Unknown | L525: 8.9 | M525: {=_xlfn.IFS(L525<=2,"Flop",L525<=5,"Average",L525<=7,"Hit",L525<=9,"Superhit",L525>9,"BlockBuster")} -> Superhit | N525: 2160463 | O525: {=_xlfn.IFS(N525<=100000,"Low",N525<=500000,"Median",N525<=1500000,"High",N525>1500000,"Very High")} -> Very High | P525: 8000000 | Q525: 213928762 | R525: =Q525-P525 -> 205928762 | S525: =IF(R525>0,"Profit","Loss") -> Profit | T525: 34475 | U525: Quentin Tarantino | V525: 34475 | W525: =TEXT(V525,"MMMM") -> May | X525: =TEXT(V525,"YYYY") -> 1994 | Y525: =VALUE(X525) -> 1994 | Z525: =TEXT(V525,"d") -> 21 | AA525: =VALUE(Z525) -> 21 | AB525: =TEXT(V525,"dddd") -> Saturday
A526: tt0110932 | B526: Quiz Show | C526: Quiz Show | D526: 0 | E526: 133 | F526: =INT(E526/60) -> 2 | G526: =MOD(E526,60) -> 13 | H526: {=_xlfn.IFS(E526<=80,"Series",E526<=120,"TV Movie",E526>120,"Long Movie")} -> Long Movie | I526: Biography | J526: Drama | K526: History | L526: 7.5 | M526: {=_xlfn.IFS(L526<=2,"Flop",L526<=5,"Average",L526<=7,"Hit",L526<=9,"Superhit",L526>9,"BlockBuster")} -> Superhit | N526: 72316 | O526: {=_xlfn.IFS(N526<=100000,"Low",N526<=500000,"Median",N526<=1500000,"High",N526>1500000,"Very High")} -> Low | P526: 31000000 | Q526: 24822619 | R526: =Q526-P526 -> -6177381 | S526: =IF(R526>0,"Profit","Loss") -> Loss | T526: NA | U526: Robert Redford | V526: NA | W526: =TEXT(V526,"MMMM") -> NA | X526: =TEXT(V526,"YYYY") -> NA | Y526: =VALUE(X526) -> #VALUE! | Z526: =TEXT(V526,"d") -> NA | AA526: =VALUE(Z526) -> #VALUE! | AB526: =TEXT(V526,"dddd") -> NA
A527: tt0110950 | B527: Reality Bites | C527: Reality Bites | D527: 0 | E527: 99 | F527: =INT(E527/60) -> 1 | G527: =MOD(E527,60) -> 39 | H527: {=_xlfn.IFS(E527<=80,"Series",E527<=120,"TV Movie",E527>120,"Long Movie")} -> TV Movie | I527: Comedy | J527: Drama | K527: Romance | L527: 6.6 | M527: {=_xlfn.IFS(L527<=2,"Flop",L527<=5,"Average",L527<=7,"Hit",L527<=9,"Superhit",L527>9,"BlockBuster")} -> Hit | N527: 52717 | O527: {=_xlfn.IFS(N527<=100000,"Low",N527<=500000,"Median",N527<=1500000,"High",N527>1500000,"Very High")} -> Low | P527: 11500000 | Q527: 33351557 | R527: =Q527-P527 -> 21851557 | S527: =IF(R527>0,"Profit","Loss") -> Profit | T527: 34335 | U527: Ben Stiller | V527: 34335 | W527: =TEXT(V527,"MMMM") -> January | X527: =TEXT(V527,"YYYY") -> 1994 | Y527: =VALUE(X527) -> 1994 | Z527: =TEXT(V527,"d") -> 1 | AA527: =VALUE(Z527) -> 1 | AB527: =TEXT(V527,"dddd") -> Saturday
A528: tt0110989 | B528: Richie Rich | C528: RiÂ¢hie RiÂ¢h | D528: 0 | E528: 95 | F528: =INT(E528/60) -> 1 | G528: =MOD(E528,60) -> 35 | H528: {=_xlfn.IFS(E528<=80,"Series",E528<=120,"TV Movie",E528>120,"Long Movie")} -> TV Movie | I528: Comedy | J528: Family | K528: Unknown | L528: 5.4 | M528: {=_xlfn.IFS(L528<=2,"Flop",L528<=5,"Average",L528<=7,"Hit",L528<=9,"Superhit",L528>9,"BlockBuster")} -> Hit | N528: 72205 | O528: {=_xlfn.IFS(N528<=100000,"Low",N528<=500000,"Median",N528<=1500000,"High",N528>1500000,"Very High")} -> Low | P528: 40000000 | Q528: 38087756 | R528: =Q528-P528 -> -1912244 | S528: =IF(R528>0,"Profit","Loss") -> Loss | T528: 34687 | U528: Donald Petrie | V528: 34687 | W528: =TEXT(V528,"MMMM") -> December | X528: =TEXT(V528,"YYYY") -> 1994 | Y528: =VALUE(X528) -> 1994 | Z528: =TEXT(V528,"d") -> 19 | AA528: =VALUE(Z528) -> 19 | AB528: =TEXT(V528,"dddd") -> Monday
A529: tt0111070 | B529: The Santa Clause | C529: The Santa Clause | D529: 0 | E529: 97 | F529: =INT(E529/60) -> 1 | G529: =MOD(E529,60) -> 37 | H529: {=_xlfn.IFS(E529<=80,"Series",E529<=120,"TV Movie",E529>120,"Long Movie")} -> TV Movie | I529: Comedy | J529: Drama | K529: Family | L529: 6.5 | M529: {=_xlfn.IFS(L529<=2,"Flop",L529<=5,"Average",L529<=7,"Hit",L529<=9,"Superhit",L529>9,"BlockBuster")} -> Hit | N529: 126968 | O529: {=_xlfn.IFS(N529<=100000,"Low",N529<=500000,"Median",N529<=1500000,"High",N529>1500000,"Very High")} -> Median | P529: 22000000 | Q529: 190539357 | R529: =Q529-P529 -> 168539357 | S529: =IF(R529>0,"Profit","Loss") -> Profit | T529: 34649 | U529: John Pasquin | V529: 34649 | W529: =TEXT(V529,"MMMM") -> November | X529: =TEXT(V529,"YYYY") -> 1994 | Y529: =VALUE(X529) -> 1994 | Z529: =TEXT(V529,"d") -> 11 | AA529: =VALUE(Z529) -> 11 | AB529: =TEXT(V529,"dddd") -> Friday
A530: tt0111149 | B530: Shallow Grave | C530: Shallow Grave | D530: 0 | E530: 89 | F530: =INT(E530/60) -> 1 | G530: =MOD(E530,60) -> 29 | H530: {=_xlfn.IFS(E530<=80,"Series",E530<=120,"TV Movie",E530>120,"Long Movie")} -> TV Movie | I530: Crime | J530: Drama | K530: Thriller | L530: 7.3 | M530: {=_xlfn.IFS(L530<=2,"Flop",L530<=5,"Average",L530<=7,"Hit",L530<=9,"Superhit",L530>9,"BlockBuster")} -> Superhit | N530: 65075 | O530: {=_xlfn.IFS(N530<=100000,"Low",N530<=500000,"Median",N530<=1500000,"High",N530>1500000,"Very High")} -> Low | P530: 2500000 | Q530: 2079569 | R530: =Q530-P530 -> -420431 | S530: =IF(R530>0,"Profit","Loss") -> Loss | T530: 34471 | U530: Danny Boyle | V530: 34471 | W530: =TEXT(V530,"MMMM") -> May | X530: =TEXT(V530,"YYYY") -> 1994 | Y530: =VALUE(X530) -> 1994 | Z530: =TEXT(V530,"d") -> 17 | AA530: =VALUE(Z530) -> 17 | AB530: =TEXT(V530,"dddd") -> Tuesday
A531: tt0111161 | B531: The Shawshank Redemption | C531: The Shawshank Redemption | D531: 0 | E531: 142 | F531: =INT(E531/60) -> 2 | G531: =MOD(E531,60) -> 22 | H531: {=_xlfn.IFS(E531<=80,"Series",E531<=120,"TV Movie",E531>120,"Long Movie")} -> Long Movie | I531: Drama | J531: Unknown | K531: Unknown | L531: 9.3 | M531: {=_xlfn.IFS(L531<=2,"Flop",L531<=5,"Average",L531<=7,"Hit",L531<=9,"Superhit",L531>9,"BlockBuster")} -> BlockBuster | N531: 2817283 | O531: {=_xlfn.IFS(N531<=100000,"Low",N531<=500000,"Median",N531<=1500000,"High",N531>1500000,"Very High")} -> Very High | P531: 25000000 | Q531: 28884716 | R531: =Q531-P531 -> 3884716 | S531: =IF(R531>0,"Profit","Loss") -> Profit | T531: 34587 | U531: Frank Darabont | V531: 34587 | W531: =TEXT(V531,"MMMM") -> September | X531: =TEXT(V531,"YYYY") -> 1994 | Y531: =VALUE(X531) -> 1994 | Z531: =TEXT(V531,"d") -> 10 | AA531: =VALUE(Z531) -> 10 | AB531: =TEXT(V531,"dddd") -> Saturday
A532: tt0111255 | B532: The Specialist | C532: The Specialist | D532: 0 | E532: 110 | F532: =INT(E532/60) -> 1 | G532: =MOD(E532,60) -> 50 | H532: {=_xlfn.IFS(E532<=80,"Series",E532<=120,"TV Movie",E532>120,"Long Movie")} -> TV Movie | I532: Action | J532: Drama | K532: Thriller | L532: 5.6 | M532: {=_xlfn.IFS(L532<=2,"Flop",L532<=5,"Average",L532<=7,"Hit",L532<=9,"Superhit",L532>9,"BlockBuster")} -> Hit | N532: 68821 | O532: {=_xlfn.IFS(N532<=100000,"Low",N532<=500000,"Median",N532<=1500000,"High",N532>1500000,"Very High")} -> Low | P532: 45000000 | Q532: 170362582 | R532: =Q532-P532 -> 125362582 | S532: =IF(R532>0,"Profit","Loss") -> Profit | T532: 34614 | U532: Luis Llosa | V532: 34614 | W532: =TEXT(V532,"MMMM") -> October | X532: =TEXT(V532,"YYYY") -> 1994 | Y532: =VALUE(X532) -> 1994 | Z532: =TEXT(V532,"d") -> 7 | AA532: =VALUE(Z532) -> 7 | AB532: =TEXT(V532,"dddd") -> Friday
A533: tt0111257 | B533: Speed | C533: Speed | D533: 0 | E533: 116 | F533: =INT(E533/60) -> 1 | G533: =MOD(E533,60) -> 56 | H533: {=_xlfn.IFS(E533<=80,"Series",E533<=120,"TV Movie",E533>120,"Long Movie")} -> TV Movie | I533: Action | J533: Adventure | K533: Thriller | L533: 7.3 | M533: {=_xlfn.IFS(L533<=2,"Flop",L533<=5,"Average",L533<=7,"Hit",L533<=9,"Superhit",L533>9,"BlockBuster")} -> Superhit | N533: 383702 | O533: {=_xlfn.IFS(N533<=100000,"Low",N533<=500000,"Median",N533<=1500000,"High",N533>1500000,"Very High")} -> Median | P533: 30000000 | Q533: 350448145 | R533: =Q533-P533 -> 320448145 | S533: =IF(R533>0,"Profit","Loss") -> Profit | T533: 34492 | U533: Jan de Bont | V533: 34492 | W533: =TEXT(V533,"MMMM") -> June | X533: =TEXT(V533,"YYYY") -> 1994 | Y533: =VALUE(X533) -> 1994 | Z533: =TEXT(V533,"d") -> 7 | AA533: =VALUE(Z533) -> 7 | AB533: =TEXT(V533,"dddd") -> Tuesday
A534: tt0111280 | B534: Star Trek: Generations | C534: Star Trek: Generations | D534: 0 | E534: 118 | F534: =INT(E534/60) -> 1 | G534: =MOD(E534,60) -> 58 | H534: {=_xlfn.IFS(E534<=80,"Series",E534<=120,"TV Movie",E534>120,"Long Movie")} -> TV Movie | I534: Action | J534: Adventure | K534: Mystery | L534: 6.6 | M534: {=_xlfn.IFS(L534<=2,"Flop",L534<=5,"Average",L534<=7,"Hit",L534<=9,"Superhit",L534>9,"BlockBuster")} -> Hit | N534: 85822 | O534: {=_xlfn.IFS(N534<=100000,"Low",N534<=500000,"Median",N534<=1500000,"High",N534>1500000,"Very High")} -> Low | P534: 35000000 | Q534: 118071125 | R534: =Q534-P534 -> 83071125 | S534: =IF(R534>0,"Profit","Loss") -> Profit | T534: 34655 | U534: David Carson | V534: 34655 | W534: =TEXT(V534,"MMMM") -> November | X534: =TEXT(V534,"YYYY") -> 1994 | Y534: =VALUE(X534) -> 1994 | Z534: =TEXT(V534,"d") -> 17 | AA534: =VALUE(Z534) -> 17 | AB534: =TEXT(V534,"dddd") -> Thursday
A535: tt0111282 | B535: Stargate | C535: Stargate | D535: 0 | E535: 116 | F535: =INT(E535/60) -> 1 | G535: =MOD(E535,60) -> 56 | H535: {=_xlfn.IFS(E535<=80,"Series",E535<=120,"TV Movie",E535>120,"Long Movie")} -> TV Movie | I535: Action | J535: Adventure | K535: Sci-Fi | L535: 7 | M535: {=_xlfn.IFS(L535<=2,"Flop",L535<=5,"Average",L535<=7,"Hit",L535<=9,"Superhit",L535>9,"BlockBuster")} -> Hit | N535: 200994 | O535: {=_xlfn.IFS(N535<=100000,"Low",N535<=500000,"Median",N535<=1500000,"High",N535>1500000,"Very High")} -> Median | P535: 55000000 | Q535: 196567262 | R535: =Q535-P535 -> 141567262 | S535: =IF(R535>0,"Profit","Loss") -> Profit | T535: 34635 | U535: Roland Emmerich | V535: 34635 | W535: =TEXT(V535,"MMMM") -> October | X535: =TEXT(V535,"YYYY") -> 1994 | Y535: =VALUE(X535) -> 1994 | Z535: =TEXT(V535,"d") -> 28 | AA535: =VALUE(Z535) -> 28 | AB535: =TEXT(V535,"dddd") -> Friday
A536: tt0111301 | B536: Street Fighter | C536: Street Fighter | D536: 0 | E536: 102 | F536: =INT(E536/60) -> 1 | G536: =MOD(E536,60) -> 42 | H536: {=_xlfn.IFS(E536<=80,"Series",E536<=120,"TV Movie",E536>120,"Long Movie")} -> TV Movie | I536: Action | J536: Adventure | K536: Comedy | L536: 4 | M536: {=_xlfn.IFS(L536<=2,"Flop",L536<=5,"Average",L536<=7,"Hit",L536<=9,"Superhit",L536>9,"BlockBuster")} -> Average | N536: 74256 | O536: {=_xlfn.IFS(N536<=100000,"Low",N536<=500000,"Median",N536<=1500000,"High",N536>1500000,"Very High")} -> Low | P536: 35000000 | Q536: 99431786 | R536: =Q536-P536 -> 64431786 | S536: =IF(R536>0,"Profit","Loss") -> Profit | T536: 34691 | U536: Steven E. de Souza | V536: 34691 | W536: =TEXT(V536,"MMMM") -> December | X536: =TEXT(V536,"YYYY") -> 1994 | Y536: =VALUE(X536) -> 1994 | Z536: =TEXT(V536,"d") -> 23 | AA536: =VALUE(Z536) -> 23 | AB536: =TEXT(V536,"dddd") -> Friday
A537: tt0111438 | B537: Timecop | C537: Timecop | D537: 0 | E537: 99 | F537: =INT(E537/60) -> 1 | G537: =MOD(E537,60) -> 39 | H537: {=_xlfn.IFS(E537<=80,"Series",E537<=120,"TV Movie",E537>120,"Long Movie")} -> TV Movie | I537: Action | J537: Crime | K537: Sci-Fi | L537: 5.9 | M537: {=_xlfn.IFS(L537<=2,"Flop",L537<=5,"Average",L537<=7,"Hit",L537<=9,"Superhit",L537>9,"BlockBuster")} -> Hit | N537: 62760 | O537: {=_xlfn.IFS(N537<=100000,"Low",N537<=500000,"Median",N537<=1500000,"High",N537>1500000,"Very High")} -> Low | P537: 27000000 | Q537: 101646581 | R537: =Q537-P537 -> 74646581 | S537: =IF(R537>0,"Profit","Loss") -> Profit | T537: 34593 | U537: Peter Hyams | V537: 34593 | W537: =TEXT(V537,"MMMM") -> September | X537: =TEXT(V537,"YYYY") -> 1994 | Y537: =VALUE(X537) -> 1994 | Z537: =TEXT(V537,"d") -> 16 | AA537: =VALUE(Z537) -> 16 | AB537: =TEXT(V537,"dddd") -> Friday
A538: tt0111503 | B538: True Lies | C538: True Lies | D538: 0 | E538: 141 | F538: =INT(E538/60) -> 2 | G538: =MOD(E538,60) -> 21 | H538: {=_xlfn.IFS(E538<=80,"Series",E538<=120,"TV Movie",E538>120,"Long Movie")} -> Long Movie | I538: Action | J538: Comedy | K538: Thriller | L538: 7.3 | M538: {=_xlfn.IFS(L538<=2,"Flop",L538<=5,"Average",L538<=7,"Hit",L538<=9,"Superhit",L538>9,"BlockBuster")} -> Superhit | N538: 274856 | O538: {=_xlfn.IFS(N538<=100000,"Low",N538<=500000,"Median",N538<=1500000,"High",N538>1500000,"Very High")} -> Median | P538: 115000000 | Q538: 378882411 | R538: =Q538-P538 -> 263882411 | S538: =IF(R538>0,"Profit","Loss") -> Profit | T538: 34527 | U538: James Cameron | V538: 34527 | W538: =TEXT(V538,"MMMM") -> July | X538: =TEXT(V538,"YYYY") -> 1994 | Y538: =VALUE(X538) -> 1994 | Z538: =TEXT(V538,"d") -> 12 | AA538: =VALUE(Z538) -> 12 | AB538: =TEXT(V538,"dddd") -> Tuesday
... A987: tt0212346 | B987: Miss Congeniality | C987: Miss Congeniality | D987: 0 | E987: 109 | F987: =INT(E987/60) -> 1 | G987: =MOD(E987,60) -> 49 | H987: {=_xlfn.IFS(E987<=80,"Series",E987<=120,"TV Movie",E987>120,"Long Movie")} -> TV Movie | I987: Action | J987: Comedy | K987: Crime | L987: 6.3 | M987: {=_xlfn.IFS(L987<=2,"Flop",L987<=5,"Average",L987<=7,"Hit",L987<=9,"Superhit",L987>9,"BlockBuster")} -> Hit | N987: 224537 | O987: {=_xlfn.IFS(N987<=100000,"Low",N987<=500000,"Median",N987<=1500000,"High",N987>1500000,"Very High")} -> Median | P987: 45000000 | Q987: 212742720 | R987: =Q987-P987 -> 167742720 | S987: =IF(R987>0,"Profit","Loss") -> Profit | T987: 36874 | U987: Donald Petrie | V987: 36874 | W987: =TEXT(V987,"MMMM") -> December | X987: =TEXT(V987,"YYYY") -> 2000 | Y987: =VALUE(X987) -> 2000 | Z987: =TEXT(V987,"d") -> 14 | AA987: =VALUE(Z987) -> 14 | AB987: =TEXT(V987,"dddd") -> Thursday
A988: tt0212712 | B988: 2046 | C988: 2046 | D988: 0 | E988: 129 | F988: =INT(E988/60) -> 2 | G988: =MOD(E988,60) -> 9 | H988: {=_xlfn.IFS(E988<=80,"Series",E988<=120,"TV Movie",E988>120,"Long Movie")} -> Long Movie | I988: Drama | J988: Romance | K988: Sci-Fi | L988: 7.4 | M988: {=_xlfn.IFS(L988<=2,"Flop",L988<=5,"Average",L988<=7,"Hit",L988<=9,"Superhit",L988>9,"BlockBuster")} -> Superhit | N988: 60667 | O988: {=_xlfn.IFS(N988<=100000,"Low",N988<=500000,"Median",N988<=1500000,"High",N988>1500000,"Very High")} -> Low | P988: 12000000 | Q988: 20205757 | R988: =Q988-P988 -> 8205757 | S988: =IF(R988>0,"Profit","Loss") -> Profit | T988: 38127 | U988: Kar-Wai Wong | V988: 38127 | W988: =TEXT(V988,"MMMM") -> May | X988: =TEXT(V988,"YYYY") -> 2004 | Y988: =VALUE(X988) -> 2004 | Z988: =TEXT(V988,"d") -> 20 | AA988: =VALUE(Z988) -> 20 | AB988: =TEXT(V988,"dddd") -> Thursday
A989: tt0212720 | B989: A.I. Artificial Intelligence | C989: A.I. Artificial Intelligence | D989: 0 | E989: 146 | F989: =INT(E989/60) -> 2 | G989: =MOD(E989,60) -> 26 | H989: {=_xlfn.IFS(E989<=80,"Series",E989<=120,"TV Movie",E989>120,"Long Movie")} -> Long Movie | I989: Drama | J989: Sci-Fi | K989: Unknown | L989: 7.2 | M989: {=_xlfn.IFS(L989<=2,"Flop",L989<=5,"Average",L989<=7,"Hit",L989<=9,"Superhit",L989>9,"BlockBuster")} -> Superhit | N989: 318645 | O989: {=_xlfn.IFS(N989<=100000,"Low",N989<=500000,"Median",N989<=1500000,"High",N989>1500000,"Very High")} -> Median | P989: 100000000 | Q989: 235926552 | R989: =Q989-P989 -> 135926552 | S989: =IF(R989>0,"Profit","Loss") -> Profit | T989: 37068 | U989: Steven Spielberg | V989: 37068 | W989: =TEXT(V989,"MMMM") -> June | X989: =TEXT(V989,"YYYY") -> 2001 | Y989: =VALUE(X989) -> 2001 | Z989: =TEXT(V989,"d") -> 26 | AA989: =VALUE(Z989) -> 26 | AB989: =TEXT(V989,"dddd") -> Tuesday
A990: tt0212985 | B990: Hannibal | C990: Hannibal | D990: 0 | E990: 131 | F990: =INT(E990/60) -> 2 | G990: =MOD(E990,60) -> 11 | H990: {=_xlfn.IFS(E990<=80,"Series",E990<=120,"TV Movie",E990>120,"Long Movie")} -> Long Movie | I990: Crime | J990: Drama | K990: Thriller | L990: 6.8 | M990: {=_xlfn.IFS(L990<=2,"Flop",L990<=5,"Average",L990<=7,"Hit",L990<=9,"Superhit",L990>9,"BlockBuster")} -> Hit | N990: 287505 | O990: {=_xlfn.IFS(N990<=100000,"Low",N990<=500000,"Median",N990<=1500000,"High",N990>1500000,"Very High")} -> Median | P990: 87000000 | Q990: 351692268 | R990: =Q990-P990 -> 264692268 | S990: =IF(R990>0,"Profit","Loss") -> Profit | T990: 36931 | U990: Ridley Scott | V990: 36931 | W990: =TEXT(V990,"MMMM") -> February | X990: =TEXT(V990,"YYYY") -> 2001 | Y990: =VALUE(X990) -> 2001 | Z990: =TEXT(V990,"d") -> 9 | AA990: =VALUE(Z990) -> 9 | AB990: =TEXT(V990,"dddd") -> Friday
A991: tt0213149 | B991: Pearl Harbor | C991: Pearl Harbor | D991: 0 | E991: 183 | F991: =INT(E991/60) -> 3 | G991: =MOD(E991,60) -> 3 | H991: {=_xlfn.IFS(E991<=80,"Series",E991<=120,"TV Movie",E991>120,"Long Movie")} -> Long Movie | I991: Action | J991: Drama | K991: History | L991: 6.2 | M991: {=_xlfn.IFS(L991<=2,"Flop",L991<=5,"Average",L991<=7,"Hit",L991<=9,"Superhit",L991>9,"BlockBuster")} -> Hit | N991: 346541 | O991: {=_xlfn.IFS(N991<=100000,"Low",N991<=500000,"Median",N991<=1500000,"High",N991>1500000,"Very High")} -> Median | P991: 140000000 | Q991: 449220945 | R991: =Q991-P991 -> 309220945 | S991: =IF(R991>0,"Profit","Loss") -> Profit | T991: 37032 | U991: Michael Bay | V991: 37032 | W991: =TEXT(V991,"MMMM") -> May | X991: =TEXT(V991,"YYYY") -> 2001 | Y991: =VALUE(X991) -> 2001 | Z991: =TEXT(V991,"d") -> 21 | AA991: =VALUE(Z991) -> 21 | AB991: =TEXT(V991,"dddd") -> Monday
A992: tt0215129 | B992: Road Trip | C992: Road Trip | D992: 0 | E992: 93 | F992: =INT(E992/60) -> 1 | G992: =MOD(E992,60) -> 33 | H992: {=_xlfn.IFS(E992<=80,"Series",E992<=120,"TV Movie",E992>120,"Long Movie")} -> TV Movie | I992: Comedy | J992: Unknown | K992: Unknown | L992: 6.5 | M992: {=_xlfn.IFS(L992<=2,"Flop",L992<=5,"Average",L992<=7,"Hit",L992<=9,"Superhit",L992>9,"BlockBuster")} -> Hit | N992: 175502 | O992: {=_xlfn.IFS(N992<=100000,"Low",N992<=500000,"Median",N992<=1500000,"High",N992>1500000,"Very High")} -> Median | P992: 16000000 | Q992: 119754278 | R992: =Q992-P992 -> 103754278 | S992: =IF(R992>0,"Profit","Loss") -> Profit | T992: 36657 | U992: Todd Phillips | V992: 36657 | W992: =TEXT(V992,"MMMM") -> May | X992: =TEXT(V992,"YYYY") -> 2000 | Y992: =VALUE(X992) -> 2000 | Z992: =TEXT(V992,"d") -> 11 | AA992: =VALUE(Z992) -> 11 | AB992: =TEXT(V992,"dddd") -> Thursday
A993: tt0215750 | B993: Enemy at the Gates | C993: Enemy at the Gates | D993: 0 | E993: 131 | F993: =INT(E993/60) -> 2 | G993: =MOD(E993,60) -> 11 | H993: {=_xlfn.IFS(E993<=80,"Series",E993<=120,"TV Movie",E993>120,"Long Movie")} -> Long Movie | I993: Action | J993: Drama | K993: War | L993: 7.5 | M993: {=_xlfn.IFS(L993<=2,"Flop",L993<=5,"Average",L993<=7,"Hit",L993<=9,"Superhit",L993>9,"BlockBuster")} -> Superhit | N993: 273308 | O993: {=_xlfn.IFS(N993<=100000,"Low",N993<=500000,"Median",N993<=1500000,"High",N993>1500000,"Very High")} -> Median | P993: 68000000 | Q993: 96976270 | R993: =Q993-P993 -> 28976270 | S993: =IF(R993>0,"Profit","Loss") -> Profit | T993: 36929 | U993: Jean-Jacques Annaud | V993: 36929 | W993: =TEXT(V993,"MMMM") -> February | X993: =TEXT(V993,"YYYY") -> 2001 | Y993: =VALUE(X993) -> 2001 | Z993: =TEXT(V993,"d") -> 7 | AA993: =VALUE(Z993) -> 7 | AB993: =TEXT(V993,"dddd") -> Wednesday
A994: tt0216216 | B994: The 6th Day | C994: The 6th Day | D994: 0 | E994: 123 | F994: =INT(E994/60) -> 2 | G994: =MOD(E994,60) -> 3 | H994: {=_xlfn.IFS(E994<=80,"Series",E994<=120,"TV Movie",E994>120,"Long Movie")} -> Long Movie | I994: Action | J994: Mystery | K994: Sci-Fi | L994: 5.9 | M994: {=_xlfn.IFS(L994<=2,"Flop",L994<=5,"Average",L994<=7,"Hit",L994<=9,"Superhit",L994>9,"BlockBuster")} -> Hit | N994: 126471 | O994: {=_xlfn.IFS(N994<=100000,"Low",N994<=500000,"Median",N994<=1500000,"High",N994>1500000,"Very High")} -> Median | P994: 82000000 | Q994: 96085477 | R994: =Q994-P994 -> 14085477 | S994: =IF(R994>0,"Profit","Loss") -> Profit | T994: 36827 | U994: Roger Spottiswoode | V994: 36827 | W994: =TEXT(V994,"MMMM") -> October | X994: =TEXT(V994,"YYYY") -> 2000 | Y994: =VALUE(X994) -> 2000 | Z994: =TEXT(V994,"d") -> 28 | AA994: =VALUE(Z994) -> 28 | AB994: =TEXT(V994,"dddd") -> Saturday
A995: tt0217505 | B995: Gangs of New York | C995: Gangs of New York | D995: 0 | E995: 167 | F995: =INT(E995/60) -> 2 | G995: =MOD(E995,60) -> 47 | H995: {=_xlfn.IFS(E995<=80,"Series",E995<=120,"TV Movie",E995>120,"Long Movie")} -> Long Movie | I995: Crime | J995: Drama | K995: Unknown | L995: 7.5 | M995: {=_xlfn.IFS(L995<=2,"Flop",L995<=5,"Average",L995<=7,"Hit",L995<=9,"Superhit",L995>9,"BlockBuster")} -> Superhit | N995: 463841 | O995: {=_xlfn.IFS(N995<=100000,"Low",N995<=500000,"Median",N995<=1500000,"High",N995>1500000,"Very High")} -> Median | P995: 100000000 | Q995: 193772504 | R995: =Q995-P995 -> 93772504 | S995: =IF(R995>0,"Profit","Loss") -> Profit | T995: 37599 | U995: Martin Scorsese | V995: 37599 | W995: =TEXT(V995,"MMMM") -> December | X995: =TEXT(V995,"YYYY") -> 2002 | Y995: =VALUE(X995) -> 2002 | Z995: =TEXT(V995,"d") -> 9 | AA995: =VALUE(Z995) -> 9 | AB995: =TEXT(V995,"dddd") -> Monday
A996: tt0217869 | B996: Unbreakable | C996: Unbreakable | D996: 0 | E996: 106 | F996: =INT(E996/60) -> 1 | G996: =MOD(E996,60) -> 46 | H996: {=_xlfn.IFS(E996<=80,"Series",E996<=120,"TV Movie",E996>120,"Long Movie")} -> TV Movie | I996: Drama | J996: Mystery | K996: Sci-Fi | L996: 7.3 | M996: {=_xlfn.IFS(L996<=2,"Flop",L996<=5,"Average",L996<=7,"Hit",L996<=9,"Superhit",L996>9,"BlockBuster")} -> Superhit | N996: 434233 | O996: {=_xlfn.IFS(N996<=100000,"Low",N996<=500000,"Median",N996<=1500000,"High",N996>1500000,"Very High")} -> Median | P996: 75000000 | Q996: 248118121 | R996: =Q996-P996 -> 173118121 | S996: =IF(R996>0,"Profit","Loss") -> Profit | T996: 36844 | U996: M. Night Shyamalan | V996: 36844 | W996: =TEXT(V996,"MMMM") -> November | X996: =TEXT(V996,"YYYY") -> 2000 | Y996: =VALUE(X996) -> 2000 | Z996: =TEXT(V996,"d") -> 14 | AA996: =VALUE(Z996) -> 14 | AB996: =TEXT(V996,"dddd") -> Tuesday
A997: tt0218839 | B997: Best in Show | C997: Best in Show | D997: 0 | E997: 90 | F997: =INT(E997/60) -> 1 | G997: =MOD(E997,60) -> 30 | H997: {=_xlfn.IFS(E997<=80,"Series",E997<=120,"TV Movie",E997>120,"Long Movie")} -> TV Movie | I997: Comedy | J997: Unknown | K997: Unknown | L997: 7.4 | M997: {=_xlfn.IFS(L997<=2,"Flop",L997<=5,"Average",L997<=7,"Hit",L997<=9,"Superhit",L997>9,"BlockBuster")} -> Superhit | N997: 65456 | O997: {=_xlfn.IFS(N997<=100000,"Low",N997<=500000,"Median",N997<=1500000,"High",N997>1500000,"Very High")} -> Low | P997: 10000000 | Q997: 20789556 | R997: =Q997-P997 -> 10789556 | S997: =IF(R997>0,"Profit","Loss") -> Profit | T997: 36777 | U997: Christopher Guest | V997: 36777 | W997: =TEXT(V997,"MMMM") -> September | X997: =TEXT(V997,"YYYY") -> 2000 | Y997: =VALUE(X997) -> 2000 | Z997: =TEXT(V997,"d") -> 8 | AA997: =VALUE(Z997) -> 8 | AB997: =TEXT(V997,"dddd") -> Friday
A998: tt0218922 | B998: Original Sin | C998: Original Sin | D998: 0 | E998: 116 | F998: =INT(E998/60) -> 1 | G998: =MOD(E998,60) -> 56 | H998: {=_xlfn.IFS(E998<=80,"Series",E998<=120,"TV Movie",E998>120,"Long Movie")} -> TV Movie | I998: Drama | J998: Mystery | K998: Romance | L998: 6 | M998: {=_xlfn.IFS(L998<=2,"Flop",L998<=5,"Average",L998<=7,"Hit",L998<=9,"Superhit",L998>9,"BlockBuster")} -> Hit | N998: 58920 | O998: {=_xlfn.IFS(N998<=100000,"Low",N998<=500000,"Median",N998<=1500000,"High",N998>1500000,"Very High")} -> Low | P998: 42000000 | Q998: 35402320 | R998: =Q998-P998 -> -6597680 | S998: =IF(R998>0,"Profit","Loss") -> Loss | T998: 37083 | U998: Michael Cristofer | V998: 37083 | W998: =TEXT(V998,"MMMM") -> July | X998: =TEXT(V998,"YYYY") -> 2001 | Y998: =VALUE(X998) -> 2001 | Z998: =TEXT(V998,"d") -> 11 | AA998: =VALUE(Z998) -> 11 | AB998: =TEXT(V998,"dddd") -> Wednesday
A999: tt0218967 | B999: The Family Man | C999: The Family Man | D999: 0 | E999: 125 | F999: =INT(E999/60) -> 2 | G999: =MOD(E999,60) -> 5 | H999: {=_xlfn.IFS(E999<=80,"Series",E999<=120,"TV Movie",E999>120,"Long Movie")} -> Long Movie | I999: Comedy | J999: Drama | K999: Fantasy | L999: 6.8 | M999: {=_xlfn.IFS(L999<=2,"Flop",L999<=5,"Average",L999<=7,"Hit",L999<=9,"Superhit",L999>9,"BlockBuster")} -> Hit | N999: 115632 | O999: {=_xlfn.IFS(N999<=100000,"Low",N999<=500000,"Median",N999<=1500000,"High",N999>1500000,"Very High")} -> Median | P999: 60000000 | Q999: 124745083 | R999: =Q999-P999 -> 64745083 | S999: =IF(R999>0,"Profit","Loss") -> Profit | T999: 36872 | U999: Brett Ratner | V999: 36872 | W999: =TEXT(V999,"MMMM") -> December | X999: =TEXT(V999,"YYYY") -> 2000 | Y999: =VALUE(X999) -> 2000 | Z999: =TEXT(V999,"d") -> 12 | AA999: =VALUE(Z999) -> 12 | AB999: =TEXT(V999,"dddd") -> Tuesday
A1000: tt0219699 | B1000: The Gift | C1000: The Gift | D1000: 0 | E1000: 112 | F1000: =INT(E1000/60) -> 1 | G1000: =MOD(E1000,60) -> 52 | H1000: {=_xlfn.IFS(E1000<=80,"Series",E1000<=120,"TV Movie",E1000>120,"Long Movie")} -> TV Movie | I1000: Drama | J1000: Fantasy | K1000: Horror | L1000: 6.7 | M1000: {=_xlfn.IFS(L1000<=2,"Flop",L1000<=5,"Average",L1000<=7,"Hit",L1000<=9,"Superhit",L1000>9,"BlockBuster")} -> Hit | N1000: 73540 | O1000: {=_xlfn.IFS(N1000<=100000,"Low",N1000<=500000,"Median",N1000<=1500000,"High",N1000>1500000,"Very High")} -> Low | P1000: 10000000 | Q1000: 44567606 | R1000: =Q1000-P1000 -> 34567606 | S1000: =IF(R1000>0,"Profit","Loss") -> Profit | T1000: 36878 | U1000: Sam Raimi | V1000: 36878 | W1000: =TEXT(V1000,"MMMM") -> December | X1000: =TEXT(V1000,"YYYY") -> 2000 | Y1000: =VALUE(X1000) -> 2000 | Z1000: =TEXT(V1000,"d") -> 18 | AA1000: =VALUE(Z1000) -> 18 | AB1000: =TEXT(V1000,"dddd") -> Monday
... A1191: tt0306047 | B1191: Scary Movie 3 | C1191: Scary Movie 3 | D1191: 0 | E1191: 84 | F1191: =INT(E1191/60) -> 1 | G1191: =MOD(E1191,60) -> 24 | H1191: {=_xlfn.IFS(E1191<=80,"Series",E1191<=120,"TV Movie",E1191>120,"Long Movie")} -> TV Movie | I1191: Comedy | J1191: Unknown | K1191: Unknown | L1191: 5.5 | M1191: {=_xlfn.IFS(L1191<=2,"Flop",L1191<=5,"Average",L1191<=7,"Hit",L1191<=9,"Superhit",L1191>9,"BlockBuster")} -> Hit | N1191: 155399 | O1191: {=_xlfn.IFS(N1191<=100000,"Low",N1191<=500000,"Median",N1191<=1500000,"High",N1191>1500000,"Very High")} -> Median | P1191: 48000000 | Q1191: 220673217 | R1191: =Q1191-P1191 -> 172673217 | S1191: =IF(R1191>0,"Profit","Loss") -> Profit | T1191: 37914 | U1191: David Zucker | V1191: 37914 | W1191: =TEXT(V1191,"MMMM") -> October | X1191: =TEXT(V1191,"YYYY") -> 2003 | Y1191: =VALUE(X1191) -> 2003 | Z1191: =TEXT(V1191,"d") -> 20 | AA1191: =VALUE(Z1191) -> 20 | AB1191: =TEXT(V1191,"dddd") -> Monday
A1192: tt0307453 | B1192: Shark Tale | C1192: Shark Tale | D1192: 0 | E1192: 90 | F1192: =INT(E1192/60) -> 1 | G1192: =MOD(E1192,60) -> 30 | H1192: {=_xlfn.IFS(E1192<=80,"Series",E1192<=120,"TV Movie",E1192>120,"Long Movie")} -> TV Movie | I1192: Adventure | J1192: Animation | K1192: Comedy | L1192: 6 | M1192: {=_xlfn.IFS(L1192<=2,"Flop",L1192<=5,"Average",L1192<=7,"Hit",L1192<=9,"Superhit",L1192>9,"BlockBuster")} -> Hit | N1192: 194771 | O1192: {=_xlfn.IFS(N1192<=100000,"Low",N1192<=500000,"Median",N1192<=1500000,"High",N1192>1500000,"Very High")} -> Median | P1192: 75000000 | Q1192: 374583879 | R1192: =Q1192-P1192 -> 299583879 | S1192: =IF(R1192>0,"Profit","Loss") -> Profit | T1192: NA | U1192: Bibo Bergeron, Vicky Jenson, Rob Letterman | V1192: NA | W1192: =TEXT(V1192,"MMMM") -> NA | X1192: =TEXT(V1192,"YYYY") -> NA | Y1192: =VALUE(X1192) -> #VALUE! | Z1192: =TEXT(V1192,"d") -> NA | AA1192: =VALUE(Z1192) -> #VALUE! | AB1192: =TEXT(V1192,"dddd") -> NA
A1193: tt0307479 | B1193: Solaris | C1193: Solaris | D1193: 0 | E1193: 99 | F1193: =INT(E1193/60) -> 1 | G1193: =MOD(E1193,60) -> 39 | H1193: {=_xlfn.IFS(E1193<=80,"Series",E1193<=120,"TV Movie",E1193>120,"Long Movie")} -> TV Movie | I1193: Drama | J1193: Mystery | K1193: Romance | L1193: 6.2 | M1193: {=_xlfn.IFS(L1193<=2,"Flop",L1193<=5,"Average",L1193<=7,"Hit",L1193<=9,"Superhit",L1193>9,"BlockBuster")} -> Hit | N1193: 85320 | O1193: {=_xlfn.IFS(N1193<=100000,"Low",N1193<=500000,"Median",N1193<=1500000,"High",N1193>1500000,"Very High")} -> Low | P1193: 47000000 | Q1193: 30002758 | R1193: =Q1193-P1193 -> -16997242 | S1193: =IF(R1193>0,"Profit","Loss") -> Loss | T1193: 37579 | U1193: Steven Soderbergh | V1193: 37579 | W1193: =TEXT(V1193,"MMMM") -> November | X1193: =TEXT(V1193,"YYYY") -> 2002 | Y1193: =VALUE(X1193) -> 2002 | Z1193: =TEXT(V1193,"d") -> 19 | AA1193: =VALUE(Z1193) -> 19 | AB1193: =TEXT(V1193,"dddd") -> Tuesday
A1194: tt0307901 | B1194: 25th Hour | C1194: 25th Hour | D1194: 0 | E1194: 135 | F1194: =INT(E1194/60) -> 2 | G1194: =MOD(E1194,60) -> 15 | H1194: {=_xlfn.IFS(E1194<=80,"Series",E1194<=120,"TV Movie",E1194>120,"Long Movie")} -> Long Movie | I1194: Drama | J1194: Unknown | K1194: Unknown | L1194: 7.6 | M1194: {=_xlfn.IFS(L1194<=2,"Flop",L1194<=5,"Average",L1194<=7,"Hit",L1194<=9,"Superhit",L1194>9,"BlockBuster")} -> Superhit | N1194: 183164 | O1194: {=_xlfn.IFS(N1194<=100000,"Low",N1194<=500000,"Median",N1194<=1500000,"High",N1194>1500000,"Very High")} -> Median | P1194: 5000000 | Q1194: 23932055 | R1194: =Q1194-P1194 -> 18932055 | S1194: =IF(R1194>0,"Profit","Loss") -> Profit | T1194: 37606 | U1194: Spike Lee | V1194: 37606 | W1194: =TEXT(V1194,"MMMM") -> December | X1194: =TEXT(V1194,"YYYY") -> 2002 | Y1194: =VALUE(X1194) -> 2002 | Z1194: =TEXT(V1194,"d") -> 16 | AA1194: =VALUE(Z1194) -> 16 | AB1194: =TEXT(V1194,"dddd") -> Monday
A1195: tt0307987 | B1195: Bad Santa | C1195: Bad Santa | D1195: 0 | E1195: 92 | F1195: =INT(E1195/60) -> 1 | G1195: =MOD(E1195,60) -> 32 | H1195: {=_xlfn.IFS(E1195<=80,"Series",E1195<=120,"TV Movie",E1195>120,"Long Movie")} -> TV Movie | I1195: Comedy | J1195: Crime | K1195: Drama | L1195: 7.1 | M1195: {=_xlfn.IFS(L1195<=2,"Flop",L1195<=5,"Average",L1195<=7,"Hit",L1195<=9,"Superhit",L1195>9,"BlockBuster")} -> Superhit | N1195: 150117 | O1195: {=_xlfn.IFS(N1195<=100000,"Low",N1195<=500000,"Median",N1195<=1500000,"High",N1195>1500000,"Very High")} -> Median | P1195: 23000000 | Q1195: 76490720 | R1195: =Q1195-P1195 -> 53490720 | S1195: =IF(R1195>0,"Profit","Loss") -> Profit | T1195: 37943 | U1195: Terry Zwigoff | V1195: 37943 | W1195: =TEXT(V1195,"MMMM") -> November | X1195: =TEXT(V1195,"YYYY") -> 2003 | Y1195: =VALUE(X1195) -> 2003 | Z1195: =TEXT(V1195,"d") -> 18 | AA1195: =VALUE(Z1195) -> 18 | AB1195: =TEXT(V1195,"dddd") -> Tuesday
A1196: tt0308644 | B1196: Finding Neverland | C1196: Finding Neverland | D1196: 0 | E1196: 106 | F1196: =INT(E1196/60) -> 1 | G1196: =MOD(E1196,60) -> 46 | H1196: {=_xlfn.IFS(E1196<=80,"Series",E1196<=120,"TV Movie",E1196>120,"Long Movie")} -> TV Movie | I1196: Biography | J1196: Drama | K1196: Family | L1196: 7.7 | M1196: {=_xlfn.IFS(L1196<=2,"Flop",L1196<=5,"Average",L1196<=7,"Hit",L1196<=9,"Superhit",L1196>9,"BlockBuster")} -> Superhit | N1196: 210506 | O1196: {=_xlfn.IFS(N1196<=100000,"Low",N1196<=500000,"Median",N1196<=1500000,"High",N1196>1500000,"Very High")} -> Median | P1196: 25000000 | Q1196: 116650613 | R1196: =Q1196-P1196 -> 91650613 | S1196: =IF(R1196>0,"Profit","Loss") -> Profit | T1196: 38234 | U1196: Marc Forster | V1196: 38234 | W1196: =TEXT(V1196,"MMMM") -> September | X1196: =TEXT(V1196,"YYYY") -> 2004 | Y1196: =VALUE(X1196) -> 2004 | Z1196: =TEXT(V1196,"d") -> 4 | AA1196: =VALUE(Z1196) -> 4 | AB1196: =TEXT(V1196,"dddd") -> Saturday
A1197: tt0309593 | B1197: Final Destination 2 | C1197: Final Destination 2 | D1197: 0 | E1197: 90 | F1197: =INT(E1197/60) -> 1 | G1197: =MOD(E1197,60) -> 30 | H1197: {=_xlfn.IFS(E1197<=80,"Series",E1197<=120,"TV Movie",E1197>120,"Long Movie")} -> TV Movie | I1197: Horror | J1197: Thriller | K1197: Unknown | L1197: 6.2 | M1197: {=_xlfn.IFS(L1197<=2,"Flop",L1197<=5,"Average",L1197<=7,"Hit",L1197<=9,"Superhit",L1197>9,"BlockBuster")} -> Hit | N1197: 178305 | O1197: {=_xlfn.IFS(N1197<=100000,"Low",N1197<=500000,"Median",N1197<=1500000,"High",N1197>1500000,"Very High")} -> Median | P1197: 26000000 | Q1197: 90941129 | R1197: =Q1197-P1197 -> 64941129 | S1197: =IF(R1197>0,"Profit","Loss") -> Profit | T1197: 37651 | U1197: David R. Ellis | V1197: 37651 | W1197: =TEXT(V1197,"MMMM") -> January | X1197: =TEXT(V1197,"YYYY") -> 2003 | Y1197: =VALUE(X1197) -> 2003 | Z1197: =TEXT(V1197,"d") -> 30 | AA1197: =VALUE(Z1197) -> 30 | AB1197: =TEXT(V1197,"dddd") -> Thursday
A1198: tt0309698 | B1198: Identity | C1198: Identity | D1198: 0 | E1198: 90 | F1198: =INT(E1198/60) -> 1 | G1198: =MOD(E1198,60) -> 30 | H1198: {=_xlfn.IFS(E1198<=80,"Series",E1198<=120,"TV Movie",E1198>120,"Long Movie")} -> TV Movie | I1198: Mystery | J1198: Thriller | K1198: Unknown | L1198: 7.3 | M1198: {=_xlfn.IFS(L1198<=2,"Flop",L1198<=5,"Average",L1198<=7,"Hit",L1198<=9,"Superhit",L1198>9,"BlockBuster")} -> Superhit | N1198: 262068 | O1198: {=_xlfn.IFS(N1198<=100000,"Low",N1198<=500000,"Median",N1198<=1500000,"High",N1198>1500000,"Very High")} -> Median | P1198: 28000000 | Q1198: 90259536 | R1198: =Q1198-P1198 -> 62259536 | S1198: =IF(R1198>0,"Profit","Loss") -> Profit | T1198: 37734 | U1198: James Mangold | V1198: 37734 | W1198: =TEXT(V1198,"MMMM") -> April | X1198: =TEXT(V1198,"YYYY") -> 2003 | Y1198: =VALUE(X1198) -> 2003 | Z1198: =TEXT(V1198,"d") -> 23 | AA1198: =VALUE(Z1198) -> 23 | AB1198: =TEXT(V1198,"dddd") -> Wednesday
A1199: tt0309987 | B1199: The Dreamers | C1199: The Dreamers | D1199: 0 | E1199: 115 | F1199: =INT(E1199/60) -> 1 | G1199: =MOD(E1199,60) -> 55 | H1199: {=_xlfn.IFS(E1199<=80,"Series",E1199<=120,"TV Movie",E1199>120,"Long Movie")} -> TV Movie | I1199: Drama | J1199: Romance | K1199: Unknown | L1199: 7.1 | M1199: {=_xlfn.IFS(L1199<=2,"Flop",L1199<=5,"Average",L1199<=7,"Hit",L1199<=9,"Superhit",L1199>9,"BlockBuster")} -> Superhit | N1199: 128480 | O1199: {=_xlfn.IFS(N1199<=100000,"Low",N1199<=500000,"Median",N1199<=1500000,"High",N1199>1500000,"Very High")} -> Median | P1199: 15000000 | Q1199: 24152155 | R1199: =Q1199-P1199 -> 9152155 | S1199: =IF(R1199>0,"Profit","Loss") -> Profit | T1199: 37865 | U1199: Bernardo Bertolucci | V1199: 37865 | W1199: =TEXT(V1199,"MMMM") -> September | X1199: =TEXT(V1199,"YYYY") -> 2003 | Y1199: =VALUE(X1199) -> 2003 | Z1199: =TEXT(V1199,"d") -> 1 | AA1199: =VALUE(Z1199) -> 1 | AB1199: =TEXT(V1199,"dddd") -> Monday
A1200: tt0310775 | B1200: Sympathy for Mr. Vengeance | C1200: Boksuneun naui geot | D1200: 0 | E1200: 129 | F1200: =INT(E1200/60) -> 2 | G1200: =MOD(E1200,60) -> 9 | H1200: {=_xlfn.IFS(E1200<=80,"Series",E1200<=120,"TV Movie",E1200>120,"Long Movie")} -> Long Movie | I1200: Crime | J1200: Drama | K1200: Thriller | L1200: 7.5 | M1200: {=_xlfn.IFS(L1200<=2,"Flop",L1200<=5,"Average",L1200<=7,"Hit",L1200<=9,"Superhit",L1200>9,"BlockBuster")} -> Superhit | N1200: 73577 | O1200: {=_xlfn.IFS(N1200<=100000,"Low",N1200<=500000,"Median",N1200<=1500000,"High",N1200>1500000,"Very High")} -> Low | P1200: 4000000 | Q1200: 2046061 | R1200: =Q1200-P1200 -> -1953939 | S1200: =IF(R1200>0,"Profit","Loss") -> Loss | T1200: 37344 | U1200: Park Chan-wook | V1200: 37344 | W1200: =TEXT(V1200,"MMMM") -> March | X1200: =TEXT(V1200,"YYYY") -> 2002 | Y1200: =VALUE(X1200) -> 2002 | Z1200: =TEXT(V1200,"d") -> 29 | AA1200: =VALUE(Z1200) -> 29 | AB1200: =TEXT(V1200,"dddd") -> Friday
A1201: tt0310793 | B1201: Bowling for Columbine | C1201: Bowling for Columbine | D1201: 0 | E1201: 120 | F1201: =INT(E1201/60) -> 2 | G1201: =MOD(E1201,60) -> 0 | H1201: {=_xlfn.IFS(E1201<=80,"Series",E1201<=120,"TV Movie",E1201>120,"Long Movie")} -> TV Movie | I1201: Crime | J1201: Documentary | K1201: Drama | L1201: 8 | M1201: {=_xlfn.IFS(L1201<=2,"Flop",L1201<=5,"Average",L1201<=7,"Hit",L1201<=9,"Superhit",L1201>9,"BlockBuster")} -> Superhit | N1201: 147608 | O1201: {=_xlfn.IFS(N1201<=100000,"Low",N1201<=500000,"Median",N1201<=1500000,"High",N1201>1500000,"Very High")} -> Median | P1201: 4000000 | Q1201: 58011975 | R1201: =Q1201-P1201 -> 54011975 | S1201: =IF(R1201>0,"Profit","Loss") -> Profit | T1201: 37392 | U1201: Michael Moore | V1201: 37392 | W1201: =TEXT(V1201,"MMMM") -> May | X1201: =TEXT(V1201,"YYYY") -> 2002 | Y1201: =VALUE(X1201) -> 2002 | Z1201: =TEXT(V1201,"d") -> 16 | AA1201: =VALUE(Z1201) -> 16 | AB1201: =TEXT(V1201,"dddd") -> Thursday
A1202: tt0311113 | B1202: Master and Commander: The Far Side of the World | C1202: Master and Commander: The Far Side of the World | D1202: 0 | E1202: 138 | F1202: =INT(E1202/60) -> 2 | G1202: =MOD(E1202,60) -> 18 | H1202: {=_xlfn.IFS(E1202<=80,"Series",E1202<=120,"TV Movie",E1202>120,"Long Movie")} -> Long Movie | I1202: Action | J1202: Adventure | K1202: Drama | L1202: 7.5 | M1202: {=_xlfn.IFS(L1202<=2,"Flop",L1202<=5,"Average",L1202<=7,"Hit",L1202<=9,"Superhit",L1202>9,"BlockBuster")} -> Superhit | N1202: 232865 | O1202: {=_xlfn.IFS(N1202<=100000,"Low",N1202<=500000,"Median",N1202<=1500000,"High",N1202>1500000,"Very High")} -> Median | P1202: 150000000 | Q1202: 211622535 | R1202: =Q1202-P1202 -> 61622535 | S1202: =IF(R1202>0,"Profit","Loss") -> Profit | T1202: 37936 | U1202: Peter Weir | V1202: 37936 | W1202: =TEXT(V1202,"MMMM") -> November | X1202: =TEXT(V1202,"YYYY") -> 2003 | Y1202: =VALUE(X1202) -> 2003 | Z1202: =TEXT(V1202,"d") -> 11 | AA1202: =VALUE(Z1202) -> 11 | AB1202: =TEXT(V1202,"dddd") -> Tuesday
A1203: tt0311289 | B1203: Holes | C1203: Holes | D1203: 0 | E1203: 117 | F1203: =INT(E1203/60) -> 1 | G1203: =MOD(E1203,60) -> 57 | H1203: {=_xlfn.IFS(E1203<=80,"Series",E1203<=120,"TV Movie",E1203>120,"Long Movie")} -> TV Movie | I1203: Adventure | J1203: Comedy | K1203: Drama | L1203: 7 | M1203: {=_xlfn.IFS(L1203<=2,"Flop",L1203<=5,"Average",L1203<=7,"Hit",L1203<=9,"Superhit",L1203>9,"BlockBuster")} -> Hit | N1203: 97228 | O1203: {=_xlfn.IFS(N1203<=100000,"Low",N1203<=500000,"Median",N1203<=1500000,"High",N1203>1500000,"Very High")} -> Low | P1203: 20000000 | Q1203: 71406573 | R1203: =Q1203-P1203 -> 51406573 | S1203: =IF(R1203>0,"Profit","Loss") -> Profit | T1203: 37722 | U1203: Andrew Davis | V1203: 37722 | W1203: =TEXT(V1203,"MMMM") -> April | X1203: =TEXT(V1203,"YYYY") -> 2003 | Y1203: =VALUE(X1203) -> 2003 | Z1203: =TEXT(V1203,"d") -> 11 | AA1203: =VALUE(Z1203) -> 11 | AB1203: =TEXT(V1203,"dddd") -> Friday
A1204: tt0311429 | B1204: The League of Extraordinary Gentlemen | C1204: The League of Extraordinary Gentlemen | D1204: 0 | E1204: 110 | F1204: =INT(E1204/60) -> 1 | G1204: =MOD(E1204,60) -> 50 | H1204: {=_xlfn.IFS(E1204<=80,"Series",E1204<=120,"TV Movie",E1204>120,"Long Movie")} -> TV Movie | I1204: Action | J1204: Adventure | K1204: Fantasy | L1204: 5.8 | M1204: {=_xlfn.IFS(L1204<=2,"Flop",L1204<=5,"Average",L1204<=7,"Hit",L1204<=9,"Superhit",L1204>9,"BlockBuster")} -> Hit | N1204: 181832 | O1204: {=_xlfn.IFS(N1204<=100000,"Low",N1204<=500000,"Median",N1204<=1500000,"High",N1204>1500000,"Very High")} -> Median | P1204: 78000000 | Q1204: 179265204 | R1204: =Q1204-P1204 -> 101265204 | S1204: =IF(R1204>0,"Profit","Loss") -> Profit | T1204: 37813 | U1204: Stephen Norrington | V1204: 37813 | W1204: =TEXT(V1204,"MMMM") -> July | X1204: =TEXT(V1204,"YYYY") -> 2003 | Y1204: =VALUE(X1204) -> 2003 | Z1204: =TEXT(V1204,"d") -> 11 | AA1204: =VALUE(Z1204) -> 11 | AB1204: =TEXT(V1204,"dddd") -> Friday
... A1299: tt0348150 | B1299: Superman Returns | C1299: Superman Returns | D1299: 0 | E1299: 154 | F1299: =INT(E1299/60) -> 2 | G1299: =MOD(E1299,60) -> 34 | H1299: {=_xlfn.IFS(E1299<=80,"Series",E1299<=120,"TV Movie",E1299>120,"Long Movie")} -> Long Movie | I1299: Action | J1299: Adventure | K1299: Sci-Fi | L1299: 6.1 | M1299: {=_xlfn.IFS(L1299<=2,"Flop",L1299<=5,"Average",L1299<=7,"Hit",L1299<=9,"Superhit",L1299>9,"BlockBuster")} -> Hit | N1299: 289349 | O1299: {=_xlfn.IFS(N1299<=100000,"Low",N1299<=500000,"Median",N1299<=1500000,"High",N1299>1500000,"Very High")} -> Median | P1299: 270000000 | Q1299: 391081192 | R1299: =Q1299-P1299 -> 121081192 | S1299: =IF(R1299>0,"Profit","Loss") -> Profit | T1299: 38889 | U1299: Bryan Singer | V1299: 38889 | W1299: =TEXT(V1299,"MMMM") -> June | X1299: =TEXT(V1299,"YYYY") -> 2006 | Y1299: =VALUE(X1299) -> 2006 | Z1299: =TEXT(V1299,"d") -> 21 | AA1299: =VALUE(Z1299) -> 21 | AB1299: =TEXT(V1299,"dddd") -> Wednesday
A1300: tt0348333 | B1300: Waiting... | C1300: Waiting... | D1300: 0 | E1300: 94 | F1300: =INT(E1300/60) -> 1 | G1300: =MOD(E1300,60) -> 34 | H1300: {=_xlfn.IFS(E1300<=80,"Series",E1300<=120,"TV Movie",E1300>120,"Long Movie")} -> TV Movie | I1300: Comedy | J1300: Unknown | K1300: Unknown | L1300: 6.7 | M1300: {=_xlfn.IFS(L1300<=2,"Flop",L1300<=5,"Average",L1300<=7,"Hit",L1300<=9,"Superhit",L1300>9,"BlockBuster")} -> Hit | N1300: 103903 | O1300: {=_xlfn.IFS(N1300<=100000,"Low",N1300<=500000,"Median",N1300<=1500000,"High",N1300>1500000,"Very High")} -> Median | P1300: 3000000 | Q1300: 18637690 | R1300: =Q1300-P1300 -> 15637690 | S1300: =IF(R1300>0,"Profit","Loss") -> Profit | T1300: NA | U1300: Rob McKittrick | V1300: NA | W1300: =TEXT(V1300,"MMMM") -> NA | X1300: =TEXT(V1300,"YYYY") -> NA | Y1300: =VALUE(X1300) -> #VALUE! | Z1300: =TEXT(V1300,"d") -> NA | AA1300: =VALUE(Z1300) -> #VALUE! | AB1300: =TEXT(V1300,"dddd") -> NA
A1301: tt0348836 | B1301: Gothika | C1301: Gothika | D1301: 0 | E1301: 98 | F1301: =INT(E1301/60) -> 1 | G1301: =MOD(E1301,60) -> 38 | H1301: {=_xlfn.IFS(E1301<=80,"Series",E1301<=120,"TV Movie",E1301>120,"Long Movie")} -> TV Movie | I1301: Horror | J1301: Mystery | K1301: Thriller | L1301: 5.8 | M1301: {=_xlfn.IFS(L1301<=2,"Flop",L1301<=5,"Average",L1301<=7,"Hit",L1301<=9,"Superhit",L1301>9,"BlockBuster")} -> Hit | N1301: 117496 | O1301: {=_xlfn.IFS(N1301<=100000,"Low",N1301<=500000,"Median",N1301<=1500000,"High",N1301>1500000,"Very High")} -> Median | P1301: 40000000 | Q1301: 141591324 | R1301: =Q1301-P1301 -> 101591324 | S1301: =IF(R1301>0,"Profit","Loss") -> Profit | T1301: 37938 | U1301: Mathieu Kassovitz | V1301: 37938 | W1301: =TEXT(V1301,"MMMM") -> November | X1301: =TEXT(V1301,"YYYY") -> 2003 | Y1301: =VALUE(X1301) -> 2003 | Z1301: =TEXT(V1301,"d") -> 13 | AA1301: =VALUE(Z1301) -> 13 | AB1301: =TEXT(V1301,"dddd") -> Thursday
A1302: tt0349205 | B1302: Cheaper by the Dozen | C1302: Cheaper by the Dozen | D1302: 0 | E1302: 98 | F1302: =INT(E1302/60) -> 1 | G1302: =MOD(E1302,60) -> 38 | H1302: {=_xlfn.IFS(E1302<=80,"Series",E1302<=120,"TV Movie",E1302>120,"Long Movie")} -> TV Movie | I1302: Comedy | J1302: Family | K1302: Unknown | L1302: 5.9 | M1302: {=_xlfn.IFS(L1302<=2,"Flop",L1302<=5,"Average",L1302<=7,"Hit",L1302<=9,"Superhit",L1302>9,"BlockBuster")} -> Hit | N1302: 107166 | O1302: {=_xlfn.IFS(N1302<=100000,"Low",N1302<=500000,"Median",N1302<=1500000,"High",N1302>1500000,"Very High")} -> Median | P1302: 40000000 | Q1302: 190538630 | R1302: =Q1302-P1302 -> 150538630 | S1302: =IF(R1302>0,"Profit","Loss") -> Profit | T1302: 37947 | U1302: Shawn Levy | V1302: 37947 | W1302: =TEXT(V1302,"MMMM") -> November | X1302: =TEXT(V1302,"YYYY") -> 2003 | Y1302: =VALUE(X1302) -> 2003 | Z1302: =TEXT(V1302,"d") -> 22 | AA1302: =VALUE(Z1302) -> 22 | AB1302: =TEXT(V1302,"dddd") -> Saturday
A1303: tt0349683 | B1303: King Arthur | C1303: King Arthur | D1303: 0 | E1303: 126 | F1303: =INT(E1303/60) -> 2 | G1303: =MOD(E1303,60) -> 6 | H1303: {=_xlfn.IFS(E1303<=80,"Series",E1303<=120,"TV Movie",E1303>120,"Long Movie")} -> Long Movie | I1303: Action | J1303: Adventure | K1303: Drama | L1303: 6.3 | M1303: {=_xlfn.IFS(L1303<=2,"Flop",L1303<=5,"Average",L1303<=7,"Hit",L1303<=9,"Superhit",L1303>9,"BlockBuster")} -> Hit | N1303: 173873 | O1303: {=_xlfn.IFS(N1303<=100000,"Low",N1303<=500000,"Median",N1303<=1500000,"High",N1303>1500000,"Very High")} -> Median | P1303: 120000000 | Q1303: 203567857 | R1303: =Q1303-P1303 -> 83567857 | S1303: =IF(R1303>0,"Profit","Loss") -> Profit | T1303: 38166 | U1303: Antoine Fuqua | V1303: 38166 | W1303: =TEXT(V1303,"MMMM") -> June | X1303: =TEXT(V1303,"YYYY") -> 2004 | Y1303: =VALUE(X1303) -> 2004 | Z1303: =TEXT(V1303,"d") -> 28 | AA1303: =VALUE(Z1303) -> 28 | AB1303: =TEXT(V1303,"dddd") -> Monday
A1304: tt0349710 | B1304: Ladder 49 | C1304: Ladder 49 | D1304: 0 | E1304: 115 | F1304: =INT(E1304/60) -> 1 | G1304: =MOD(E1304,60) -> 55 | H1304: {=_xlfn.IFS(E1304<=80,"Series",E1304<=120,"TV Movie",E1304>120,"Long Movie")} -> TV Movie | I1304: Action | J1304: Drama | K1304: Thriller | L1304: 6.5 | M1304: {=_xlfn.IFS(L1304<=2,"Flop",L1304<=5,"Average",L1304<=7,"Hit",L1304<=9,"Superhit",L1304>9,"BlockBuster")} -> Hit | N1304: 58971 | O1304: {=_xlfn.IFS(N1304<=100000,"Low",N1304<=500000,"Median",N1304<=1500000,"High",N1304>1500000,"Very High")} -> Low | P1304: 45000000 | Q1304: 100572044 | R1304: =Q1304-P1304 -> 55572044 | S1304: =IF(R1304>0,"Profit","Loss") -> Profit | T1304: 38250 | U1304: Jay Russell | V1304: 38250 | W1304: =TEXT(V1304,"MMMM") -> September | X1304: =TEXT(V1304,"YYYY") -> 2004 | Y1304: =VALUE(X1304) -> 2004 | Z1304: =TEXT(V1304,"d") -> 20 | AA1304: =VALUE(Z1304) -> 20 | AB1304: =TEXT(V1304,"dddd") -> Monday
A1305: tt0349825 | B1305: Miracle | C1305: Miracle | D1305: 0 | E1305: 135 | F1305: =INT(E1305/60) -> 2 | G1305: =MOD(E1305,60) -> 15 | H1305: {=_xlfn.IFS(E1305<=80,"Series",E1305<=120,"TV Movie",E1305>120,"Long Movie")} -> Long Movie | I1305: Biography | J1305: Drama | K1305: History | L1305: 7.4 | M1305: {=_xlfn.IFS(L1305<=2,"Flop",L1305<=5,"Average",L1305<=7,"Hit",L1305<=9,"Superhit",L1305>9,"BlockBuster")} -> Superhit | N1305: 57540 | O1305: {=_xlfn.IFS(N1305<=100000,"Low",N1305<=500000,"Median",N1305<=1500000,"High",N1305>1500000,"Very High")} -> Low | P1305: 28000000 | Q1305: 64445708 | R1305: =Q1305-P1305 -> 36445708 | S1305: =IF(R1305>0,"Profit","Loss") -> Profit | T1305: 38019 | U1305: Gavin O'Connor | V1305: 38019 | W1305: =TEXT(V1305,"MMMM") -> February | X1305: =TEXT(V1305,"YYYY") -> 2004 | Y1305: =VALUE(X1305) -> 2004 | Z1305: =TEXT(V1305,"d") -> 2 | AA1305: =VALUE(Z1305) -> 2 | AB1305: =TEXT(V1305,"dddd") -> Monday
A1306: tt0349903 | B1306: Ocean's Twelve | C1306: Ocean's Twelve | D1306: 0 | E1306: 125 | F1306: =INT(E1306/60) -> 2 | G1306: =MOD(E1306,60) -> 5 | H1306: {=_xlfn.IFS(E1306<=80,"Series",E1306<=120,"TV Movie",E1306>120,"Long Movie")} -> Long Movie | I1306: Crime | J1306: Thriller | K1306: Unknown | L1306: 6.5 | M1306: {=_xlfn.IFS(L1306<=2,"Flop",L1306<=5,"Average",L1306<=7,"Hit",L1306<=9,"Superhit",L1306>9,"BlockBuster")} -> Hit | N1306: 407294 | O1306: {=_xlfn.IFS(N1306<=100000,"Low",N1306<=500000,"Median",N1306<=1500000,"High",N1306>1500000,"Very High")} -> Median | P1306: 110000000 | Q1306: 362744280 | R1306: =Q1306-P1306 -> 252744280 | S1306: =IF(R1306>0,"Profit","Loss") -> Profit | T1306: 38329 | U1306: Steven Soderbergh | V1306: 38329 | W1306: =TEXT(V1306,"MMMM") -> December | X1306: =TEXT(V1306,"YYYY") -> 2004 | Y1306: =VALUE(X1306) -> 2004 | Z1306: =TEXT(V1306,"d") -> 8 | AA1306: =VALUE(Z1306) -> 8 | AB1306: =TEXT(V1306,"dddd") -> Wednesday
A1307: tt0350258 | B1307: Ray | C1307: Ray | D1307: 0 | E1307: 152 | F1307: =INT(E1307/60) -> 2 | G1307: =MOD(E1307,60) -> 32 | H1307: {=_xlfn.IFS(E1307<=80,"Series",E1307<=120,"TV Movie",E1307>120,"Long Movie")} -> Long Movie | I1307: Biography | J1307: Drama | K1307: Music | L1307: 7.7 | M1307: {=_xlfn.IFS(L1307<=2,"Flop",L1307<=5,"Average",L1307<=7,"Hit",L1307<=9,"Superhit",L1307>9,"BlockBuster")} -> Superhit | N1307: 154876 | O1307: {=_xlfn.IFS(N1307<=100000,"Low",N1307<=500000,"Median",N1307<=1500000,"High",N1307>1500000,"Very High")} -> Median | P1307: 40000000 | Q1307: 123971376 | R1307: =Q1307-P1307 -> 83971376 | S1307: =IF(R1307>0,"Profit","Loss") -> Profit | T1307: 38242 | U1307: Taylor Hackford | V1307: 38242 | W1307: =TEXT(V1307,"MMMM") -> September | X1307: =TEXT(V1307,"YYYY") -> 2004 | Y1307: =VALUE(X1307) -> 2004 | Z1307: =TEXT(V1307,"d") -> 12 | AA1307: =VALUE(Z1307) -> 12 | AB1307: =TEXT(V1307,"dddd") -> Sunday
A1308: tt0351283 | B1308: Madagascar | C1308: Madagascar | D1308: 0 | E1308: 86 | F1308: =INT(E1308/60) -> 1 | G1308: =MOD(E1308,60) -> 26 | H1308: {=_xlfn.IFS(E1308<=80,"Series",E1308<=120,"TV Movie",E1308>120,"Long Movie")} -> TV Movie | I1308: Adventure | J1308: Animation | K1308: Comedy | L1308: 6.9 | M1308: {=_xlfn.IFS(L1308<=2,"Flop",L1308<=5,"Average",L1308<=7,"Hit",L1308<=9,"Superhit",L1308>9,"BlockBuster")} -> Hit | N1308: 426684 | O1308: {=_xlfn.IFS(N1308<=100000,"Low",N1308<=500000,"Median",N1308<=1500000,"High",N1308>1500000,"Very High")} -> Median | P1308: 75000000 | Q1308: 542063846 | R1308: =Q1308-P1308 -> 467063846 | S1308: =IF(R1308>0,"Profit","Loss") -> Profit | T1308: 38497 | U1308: Eric Darnell, Tom McGrath | V1308: 38497 | W1308: =TEXT(V1308,"MMMM") -> May | X1308: =TEXT(V1308,"YYYY") -> 2005 | Y1308: =VALUE(X1308) -> 2005 | Z1308: =TEXT(V1308,"d") -> 25 | AA1308: =VALUE(Z1308) -> 25 | AB1308: =TEXT(V1308,"dddd") -> Wednesday
A1309: tt0351977 | B1309: Walking Tall | C1309: Walking Tall | D1309: 0 | E1309: 86 | F1309: =INT(E1309/60) -> 1 | G1309: =MOD(E1309,60) -> 26 | H1309: {=_xlfn.IFS(E1309<=80,"Series",E1309<=120,"TV Movie",E1309>120,"Long Movie")} -> TV Movie | I1309: Action | J1309: Crime | K1309: Unknown | L1309: 6.3 | M1309: {=_xlfn.IFS(L1309<=2,"Flop",L1309<=5,"Average",L1309<=7,"Hit",L1309<=9,"Superhit",L1309>9,"BlockBuster")} -> Hit | N1309: 108947 | O1309: {=_xlfn.IFS(N1309<=100000,"Low",N1309<=500000,"Median",N1309<=1500000,"High",N1309>1500000,"Very High")} -> Median | P1309: 46000000 | Q1309: 57223890 | R1309: =Q1309-P1309 -> 11223890 | S1309: =IF(R1309>0,"Profit","Loss") -> Profit | T1309: 38075 | U1309: Kevin Bray | V1309: 38075 | W1309: =TEXT(V1309,"MMMM") -> March | X1309: =TEXT(V1309,"YYYY") -> 2004 | Y1309: =VALUE(X1309) -> 2004 | Z1309: =TEXT(V1309,"d") -> 29 | AA1309: =VALUE(Z1309) -> 29 | AB1309: =TEXT(V1309,"dddd") -> Monday
A1310: tt0352248 | B1310: Cinderella Man | C1310: Cinderella Man | D1310: 0 | E1310: 144 | F1310: =INT(E1310/60) -> 2 | G1310: =MOD(E1310,60) -> 24 | H1310: {=_xlfn.IFS(E1310<=80,"Series",E1310<=120,"TV Movie",E1310>120,"Long Movie")} -> Long Movie | I1310: Biography | J1310: Drama | K1310: Romance | L1310: 8 | M1310: {=_xlfn.IFS(L1310<=2,"Flop",L1310<=5,"Average",L1310<=7,"Hit",L1310<=9,"Superhit",L1310>9,"BlockBuster")} -> Superhit | N1310: 195114 | O1310: {=_xlfn.IFS(N1310<=100000,"Low",N1310<=500000,"Median",N1310<=1500000,"High",N1310>1500000,"Very High")} -> Median | P1310: 88000000 | Q1310: 108539911 | R1310: =Q1310-P1310 -> 20539911 | S1310: =IF(R1310>0,"Profit","Loss") -> Profit | T1310: 38495 | U1310: Ron Howard | V1310: 38495 | W1310: =TEXT(V1310,"MMMM") -> May | X1310: =TEXT(V1310,"YYYY") -> 2005 | Y1310: =VALUE(X1310) -> 2005 | Z1310: =TEXT(V1310,"d") -> 23 | AA1310: =VALUE(Z1310) -> 23 | AB1310: =TEXT(V1310,"dddd") -> Monday
A1311: tt0353969 | B1311: Memories of Murder | C1311: Salinui chueok | D1311: 0 | E1311: 131 | F1311: =INT(E1311/60) -> 2 | G1311: =MOD(E1311,60) -> 11 | H1311: {=_xlfn.IFS(E1311<=80,"Series",E1311<=120,"TV Movie",E1311>120,"Long Movie")} -> Long Movie | I1311: Crime | J1311: Drama | K1311: Mystery | L1311: 8.1 | M1311: {=_xlfn.IFS(L1311<=2,"Flop",L1311<=5,"Average",L1311<=7,"Hit",L1311<=9,"Superhit",L1311>9,"BlockBuster")} -> Superhit | N1311: 206029 | O1311: {=_xlfn.IFS(N1311<=100000,"Low",N1311<=500000,"Median",N1311<=1500000,"High",N1311>1500000,"Very High")} -> Median | P1311: 2800000 | Q1311: 1204841 | R1311: =Q1311-P1311 -> -1595159 | S1311: =IF(R1311>0,"Profit","Loss") -> Loss | T1311: 37743 | U1311: Bong Joon Ho | V1311: 37743 | W1311: =TEXT(V1311,"MMMM") -> May | X1311: =TEXT(V1311,"YYYY") -> 2003 | Y1311: =VALUE(X1311) -> 2003 | Z1311: =TEXT(V1311,"d") -> 2 | AA1311: =VALUE(Z1311) -> 2 | AB1311: =TEXT(V1311,"dddd") -> Friday
A1312: tt0354899 | B1312: The Science of Sleep | C1312: La science des rÃªves | D1312: 0 | E1312: 105 | F1312: =INT(E1312/60) -> 1 | G1312: =MOD(E1312,60) -> 45 | H1312: {=_xlfn.IFS(E1312<=80,"Series",E1312<=120,"TV Movie",E1312>120,"Long Movie")} -> TV Movie | I1312: Comedy | J1312: Drama | K1312: Fantasy | L1312: 7.2 | M1312: {=_xlfn.IFS(L1312<=2,"Flop",L1312<=5,"Average",L1312<=7,"Hit",L1312<=9,"Superhit",L1312>9,"BlockBuster")} -> Superhit | N1312: 70458 | O1312: {=_xlfn.IFS(N1312<=100000,"Low",N1312<=500000,"Median",N1312<=1500000,"High",N1312>1500000,"Very High")} -> Low | P1312: 6000000 | Q1312: 15116179 | R1312: =Q1312-P1312 -> 9116179 | S1312: =IF(R1312>0,"Profit","Loss") -> Profit | T1312: 38759 | U1312: Michel Gondry | V1312: 38759 | W1312: =TEXT(V1312,"MMMM") -> February | X1312: =TEXT(V1312,"YYYY") -> 2006 | Y1312: =VALUE(X1312) -> 2006 | Z1312: =TEXT(V1312,"d") -> 11 | AA1312: =VALUE(Z1312) -> 11 | AB1312: =TEXT(V1312,"dddd") -> Saturday
... A1527: tt0416320 | B1527: Match Point | C1527: Match Point | D1527: 0 | E1527: 124 | F1527: =INT(E1527/60) -> 2 | G1527: =MOD(E1527,60) -> 4 | H1527: {=_xlfn.IFS(E1527<=80,"Series",E1527<=120,"TV Movie",E1527>120,"Long Movie")} -> Long Movie | I1527: Drama | J1527: Romance | K1527: Thriller | L1527: 7.6 | M1527: {=_xlfn.IFS(L1527<=2,"Flop",L1527<=5,"Average",L1527<=7,"Hit",L1527<=9,"Superhit",L1527>9,"BlockBuster")} -> Superhit | N1527: 225226 | O1527: {=_xlfn.IFS(N1527<=100000,"Low",N1527<=500000,"Median",N1527<=1500000,"High",N1527>1500000,"Very High")} -> Median | P1527: 15000000 | Q1527: 85638656 | R1527: =Q1527-P1527 -> 70638656 | S1527: =IF(R1527>0,"Profit","Loss") -> Profit | T1527: 38484 | U1527: Woody Allen | V1527: 38484 | W1527: =TEXT(V1527,"MMMM") -> May | X1527: =TEXT(V1527,"YYYY") -> 2005 | Y1527: =VALUE(X1527) -> 2005 | Z1527: =TEXT(V1527,"d") -> 12 | AA1527: =VALUE(Z1527) -> 12 | AB1527: =TEXT(V1527,"dddd") -> Thursday
A1528: tt0416449 | B1528: 300 | C1528: 300 | D1528: 0 | E1528: 117 | F1528: =INT(E1528/60) -> 1 | G1528: =MOD(E1528,60) -> 57 | H1528: {=_xlfn.IFS(E1528<=80,"Series",E1528<=120,"TV Movie",E1528>120,"Long Movie")} -> TV Movie | I1528: Action | J1528: Drama | K1528: Unknown | L1528: 7.6 | M1528: {=_xlfn.IFS(L1528<=2,"Flop",L1528<=5,"Average",L1528<=7,"Hit",L1528<=9,"Superhit",L1528>9,"BlockBuster")} -> Superhit | N1528: 849600 | O1528: {=_xlfn.IFS(N1528<=100000,"Low",N1528<=500000,"Median",N1528<=1500000,"High",N1528>1500000,"Very High")} -> High | P1528: 65000000 | Q1528: 456082343 | R1528: =Q1528-P1528 -> 391082343 | S1528: =IF(R1528>0,"Profit","Loss") -> Profit | T1528: 39060 | U1528: Zack Snyder | V1528: 39060 | W1528: =TEXT(V1528,"MMMM") -> December | X1528: =TEXT(V1528,"YYYY") -> 2006 | Y1528: =VALUE(X1528) -> 2006 | Z1528: =TEXT(V1528,"d") -> 9 | AA1528: =VALUE(Z1528) -> 9 | AB1528: =TEXT(V1528,"dddd") -> Saturday
A1529: tt0416508 | B1529: Becoming Jane | C1529: Becoming Jane | D1529: 0 | E1529: 120 | F1529: =INT(E1529/60) -> 2 | G1529: =MOD(E1529,60) -> 0 | H1529: {=_xlfn.IFS(E1529<=80,"Series",E1529<=120,"TV Movie",E1529>120,"Long Movie")} -> TV Movie | I1529: Biography | J1529: Drama | K1529: Romance | L1529: 7 | M1529: {=_xlfn.IFS(L1529<=2,"Flop",L1529<=5,"Average",L1529<=7,"Hit",L1529<=9,"Superhit",L1529>9,"BlockBuster")} -> Hit | N1529: 64262 | O1529: {=_xlfn.IFS(N1529<=100000,"Low",N1529<=500000,"Median",N1529<=1500000,"High",N1529>1500000,"Very High")} -> Low | P1529: 16500000 | Q1529: 37311672 | R1529: =Q1529-P1529 -> 20811672 | S1529: =IF(R1529>0,"Profit","Loss") -> Profit | T1529: 39143 | U1529: Julian Jarrold | V1529: 39143 | W1529: =TEXT(V1529,"MMMM") -> March | X1529: =TEXT(V1529,"YYYY") -> 2007 | Y1529: =VALUE(X1529) -> 2007 | Z1529: =TEXT(V1529,"d") -> 2 | AA1529: =VALUE(Z1529) -> 2 | AB1529: =TEXT(V1529,"dddd") -> Friday
A1530: tt0417148 | B1530: Snakes on a Plane | C1530: Snakes on a Plane | D1530: 0 | E1530: 105 | F1530: =INT(E1530/60) -> 1 | G1530: =MOD(E1530,60) -> 45 | H1530: {=_xlfn.IFS(E1530<=80,"Series",E1530<=120,"TV Movie",E1530>120,"Long Movie")} -> TV Movie | I1530: Action | J1530: Adventure | K1530: Crime | L1530: 5.5 | M1530: {=_xlfn.IFS(L1530<=2,"Flop",L1530<=5,"Average",L1530<=7,"Hit",L1530<=9,"Superhit",L1530>9,"BlockBuster")} -> Hit | N1530: 143393 | O1530: {=_xlfn.IFS(N1530<=100000,"Low",N1530<=500000,"Median",N1530<=1500000,"High",N1530>1500000,"Very High")} -> Median | P1530: 33000000 | Q1530: 62022014 | R1530: =Q1530-P1530 -> 29022014 | S1530: =IF(R1530>0,"Profit","Loss") -> Profit | T1530: 38946 | U1530: David R. Ellis | V1530: 38946 | W1530: =TEXT(V1530,"MMMM") -> August | X1530: =TEXT(V1530,"YYYY") -> 2006 | Y1530: =VALUE(X1530) -> 2006 | Z1530: =TEXT(V1530,"d") -> 17 | AA1530: =VALUE(Z1530) -> 17 | AB1530: =TEXT(V1530,"dddd") -> Thursday
A1531: tt0417741 | B1531: Harry Potter and the Half-Blood Prince | C1531: Harry Potter and the Half-Blood Prince | D1531: 0 | E1531: 153 | F1531: =INT(E1531/60) -> 2 | G1531: =MOD(E1531,60) -> 33 | H1531: {=_xlfn.IFS(E1531<=80,"Series",E1531<=120,"TV Movie",E1531>120,"Long Movie")} -> Long Movie | I1531: Action | J1531: Adventure | K1531: Family | L1531: 7.6 | M1531: {=_xlfn.IFS(L1531<=2,"Flop",L1531<=5,"Average",L1531<=7,"Hit",L1531<=9,"Superhit",L1531>9,"BlockBuster")} -> Superhit | N1531: 578478 | O1531: {=_xlfn.IFS(N1531<=100000,"Low",N1531<=500000,"Median",N1531<=1500000,"High",N1531>1500000,"Very High")} -> High | P1531: 250000000 | Q1531: 934770304 | R1531: =Q1531-P1531 -> 684770304 | S1531: =IF(R1531>0,"Profit","Loss") -> Profit | T1531: 40000 | U1531: David Yates | V1531: 40000 | W1531: =TEXT(V1531,"MMMM") -> July | X1531: =TEXT(V1531,"YYYY") -> 2009 | Y1531: =VALUE(X1531) -> 2009 | Z1531: =TEXT(V1531,"d") -> 6 | AA1531: =VALUE(Z1531) -> 6 | AB1531: =TEXT(V1531,"dddd") -> Monday
A1532: tt0418279 | B1532: Transformers | C1532: Transformers | D1532: 0 | E1532: 144 | F1532: =INT(E1532/60) -> 2 | G1532: =MOD(E1532,60) -> 24 | H1532: {=_xlfn.IFS(E1532<=80,"Series",E1532<=120,"TV Movie",E1532>120,"Long Movie")} -> Long Movie | I1532: Action | J1532: Adventure | K1532: Sci-Fi | L1532: 7 | M1532: {=_xlfn.IFS(L1532<=2,"Flop",L1532<=5,"Average",L1532<=7,"Hit",L1532<=9,"Superhit",L1532>9,"BlockBuster")} -> Hit | N1532: 665305 | O1532: {=_xlfn.IFS(N1532<=100000,"Low",N1532<=500000,"Median",N1532<=1500000,"High",N1532>1500000,"Very High")} -> High | P1532: 150000000 | Q1532: 709709780 | R1532: =Q1532-P1532 -> 559709780 | S1532: =IF(R1532>0,"Profit","Loss") -> Profit | T1532: 39245 | U1532: Michael Bay | V1532: 39245 | W1532: =TEXT(V1532,"MMMM") -> June | X1532: =TEXT(V1532,"YYYY") -> 2007 | Y1532: =VALUE(X1532) -> 2007 | Z1532: =TEXT(V1532,"d") -> 12 | AA1532: =VALUE(Z1532) -> 12 | AB1532: =TEXT(V1532,"dddd") -> Tuesday
A1533: tt0418689 | B1533: Flags of Our Fathers | C1533: Flags of Our Fathers | D1533: 0 | E1533: 135 | F1533: =INT(E1533/60) -> 2 | G1533: =MOD(E1533,60) -> 15 | H1533: {=_xlfn.IFS(E1533<=80,"Series",E1533<=120,"TV Movie",E1533>120,"Long Movie")} -> Long Movie | I1533: Action | J1533: Adventure | K1533: Drama | L1533: 7.1 | M1533: {=_xlfn.IFS(L1533<=2,"Flop",L1533<=5,"Average",L1533<=7,"Hit",L1533<=9,"Superhit",L1533>9,"BlockBuster")} -> Superhit | N1533: 127723 | O1533: {=_xlfn.IFS(N1533<=100000,"Low",N1533<=500000,"Median",N1533<=1500000,"High",N1533>1500000,"Very High")} -> Median | P1533: 90000000 | Q1533: 65900249 | R1533: =Q1533-P1533 -> -24099751 | S1533: =IF(R1533>0,"Profit","Loss") -> Loss | T1533: 38999 | U1533: Clint Eastwood | V1533: 38999 | W1533: =TEXT(V1533,"MMMM") -> October | X1533: =TEXT(V1533,"YYYY") -> 2006 | Y1533: =VALUE(X1533) -> 2006 | Z1533: =TEXT(V1533,"d") -> 9 | AA1533: =VALUE(Z1533) -> 9 | AB1533: =TEXT(V1533,"dddd") -> Monday
A1534: tt0418763 | B1534: Jarhead | C1534: Jarhead | D1534: 0 | E1534: 125 | F1534: =INT(E1534/60) -> 2 | G1534: =MOD(E1534,60) -> 5 | H1534: {=_xlfn.IFS(E1534<=80,"Series",E1534<=120,"TV Movie",E1534>120,"Long Movie")} -> Long Movie | I1534: Biography | J1534: Drama | K1534: War | L1534: 7 | M1534: {=_xlfn.IFS(L1534<=2,"Flop",L1534<=5,"Average",L1534<=7,"Hit",L1534<=9,"Superhit",L1534>9,"BlockBuster")} -> Hit | N1534: 202062 | O1534: {=_xlfn.IFS(N1534<=100000,"Low",N1534<=500000,"Median",N1534<=1500000,"High",N1534>1500000,"Very High")} -> Median | P1534: 72000000 | Q1534: 97076152 | R1534: =Q1534-P1534 -> 25076152 | S1534: =IF(R1534>0,"Profit","Loss") -> Profit | T1534: 38652 | U1534: Sam Mendes | V1534: 38652 | W1534: =TEXT(V1534,"MMMM") -> October | X1534: =TEXT(V1534,"YYYY") -> 2005 | Y1534: =VALUE(X1534) -> 2005 | Z1534: =TEXT(V1534,"d") -> 27 | AA1534: =VALUE(Z1534) -> 27 | AB1534: =TEXT(V1534,"dddd") -> Thursday
A1535: tt0418819 | B1535: Land of the Dead | C1535: Land of the Dead | D1535: 0 | E1535: 93 | F1535: =INT(E1535/60) -> 1 | G1535: =MOD(E1535,60) -> 33 | H1535: {=_xlfn.IFS(E1535<=80,"Series",E1535<=120,"TV Movie",E1535>120,"Long Movie")} -> TV Movie | I1535: Horror | J1535: Sci-Fi | K1535: Thriller | L1535: 6.2 | M1535: {=_xlfn.IFS(L1535<=2,"Flop",L1535<=5,"Average",L1535<=7,"Hit",L1535<=9,"Superhit",L1535>9,"BlockBuster")} -> Hit | N1535: 99717 | O1535: {=_xlfn.IFS(N1535<=100000,"Low",N1535<=500000,"Median",N1535<=1500000,"High",N1535>1500000,"Very High")} -> Low | P1535: 15000000 | Q1535: 47074133 | R1535: =Q1535-P1535 -> 32074133 | S1535: =IF(R1535>0,"Profit","Loss") -> Profit | T1535: 38521 | U1535: George A. Romero | V1535: 38521 | W1535: =TEXT(V1535,"MMMM") -> June | X1535: =TEXT(V1535,"YYYY") -> 2005 | Y1535: =VALUE(X1535) -> 2005 | Z1535: =TEXT(V1535,"d") -> 18 | AA1535: =VALUE(Z1535) -> 18 | AB1535: =TEXT(V1535,"dddd") -> Saturday
A1536: tt0419706 | B1536: Doom | C1536: Doom | D1536: 0 | E1536: 105 | F1536: =INT(E1536/60) -> 1 | G1536: =MOD(E1536,60) -> 45 | H1536: {=_xlfn.IFS(E1536<=80,"Series",E1536<=120,"TV Movie",E1536>120,"Long Movie")} -> TV Movie | I1536: Action | J1536: Horror | K1536: Sci-Fi | L1536: 5.2 | M1536: {=_xlfn.IFS(L1536<=2,"Flop",L1536<=5,"Average",L1536<=7,"Hit",L1536<=9,"Superhit",L1536>9,"BlockBuster")} -> Hit | N1536: 117478 | O1536: {=_xlfn.IFS(N1536<=100000,"Low",N1536<=500000,"Median",N1536<=1500000,"High",N1536>1500000,"Very High")} -> Median | P1536: 60000000 | Q1536: 58072119 | R1536: =Q1536-P1536 -> -1927881 | S1536: =IF(R1536>0,"Profit","Loss") -> Loss | T1536: 38645 | U1536: Andrzej Bartkowiak | V1536: 38645 | W1536: =TEXT(V1536,"MMMM") -> October | X1536: =TEXT(V1536,"YYYY") -> 2005 | Y1536: =VALUE(X1536) -> 2005 | Z1536: =TEXT(V1536,"d") -> 20 | AA1536: =VALUE(Z1536) -> 20 | AB1536: =TEXT(V1536,"dddd") -> Thursday
A1537: tt0419887 | B1537: The Kite Runner | C1537: The Kite Runner | D1537: 0 | E1537: 128 | F1537: =INT(E1537/60) -> 2 | G1537: =MOD(E1537,60) -> 8 | H1537: {=_xlfn.IFS(E1537<=80,"Series",E1537<=120,"TV Movie",E1537>120,"Long Movie")} -> Long Movie | I1537: Drama | J1537: Unknown | K1537: Unknown | L1537: 7.6 | M1537: {=_xlfn.IFS(L1537<=2,"Flop",L1537<=5,"Average",L1537<=7,"Hit",L1537<=9,"Superhit",L1537>9,"BlockBuster")} -> Superhit | N1537: 81924 | O1537: {=_xlfn.IFS(N1537<=100000,"Low",N1537<=500000,"Median",N1537<=1500000,"High",N1537>1500000,"Very High")} -> Low | P1537: 20000000 | Q1537: 75011029 | R1537: =Q1537-P1537 -> 55011029 | S1537: =IF(R1537>0,"Profit","Loss") -> Profit | T1537: 39356 | U1537: Marc Forster | V1537: 39356 | W1537: =TEXT(V1537,"MMMM") -> October | X1537: =TEXT(V1537,"YYYY") -> 2007 | Y1537: =VALUE(X1537) -> 2007 | Z1537: =TEXT(V1537,"d") -> 1 | AA1537: =VALUE(Z1537) -> 1 | AB1537: =TEXT(V1537,"dddd") -> Monday
A1538: tt0420223 | B1538: Stranger Than Fiction | C1538: Stranger Than Fiction | D1538: 0 | E1538: 113 | F1538: =INT(E1538/60) -> 1 | G1538: =MOD(E1538,60) -> 53 | H1538: {=_xlfn.IFS(E1538<=80,"Series",E1538<=120,"TV Movie",E1538>120,"Long Movie")} -> TV Movie | I1538: Comedy | J1538: Drama | K1538: Fantasy | L1538: 7.5 | M1538: {=_xlfn.IFS(L1538<=2,"Flop",L1538<=5,"Average",L1538<=7,"Hit",L1538<=9,"Superhit",L1538>9,"BlockBuster")} -> Superhit | N1538: 234573 | O1538: {=_xlfn.IFS(N1538<=100000,"Low",N1538<=500000,"Median",N1538<=1500000,"High",N1538>1500000,"Very High")} -> Median | P1538: 30000000 | Q1538: 53653224 | R1538: =Q1538-P1538 -> 23653224 | S1538: =IF(R1538>0,"Profit","Loss") -> Profit | T1538: 38969 | U1538: Marc Forster | V1538: 38969 | W1538: =TEXT(V1538,"MMMM") -> September | X1538: =TEXT(V1538,"YYYY") -> 2006 | Y1538: =VALUE(X1538) -> 2006 | Z1538: =TEXT(V1538,"d") -> 9 | AA1538: =VALUE(Z1538) -> 9 | AB1538: =TEXT(V1538,"dddd") -> Saturday
A1539: tt0420294 | B1539: The Texas Chainsaw Massacre: The Beginning | C1539: The Texas Chainsaw Massacre: The Beginning | D1539: 0 | E1539: 91 | F1539: =INT(E1539/60) -> 1 | G1539: =MOD(E1539,60) -> 31 | H1539: {=_xlfn.IFS(E1539<=80,"Series",E1539<=120,"TV Movie",E1539>120,"Long Movie")} -> TV Movie | I1539: Horror | J1539: Unknown | K1539: Unknown | L1539: 5.8 | M1539: {=_xlfn.IFS(L1539<=2,"Flop",L1539<=5,"Average",L1539<=7,"Hit",L1539<=9,"Superhit",L1539>9,"BlockBuster")} -> Hit | N1539: 76364 | O1539: {=_xlfn.IFS(N1539<=100000,"Low",N1539<=500000,"Median",N1539<=1500000,"High",N1539>1500000,"Very High")} -> Low | P1539: 16000000 | Q1539: 51764406 | R1539: =Q1539-P1539 -> 35764406 | S1539: =IF(R1539>0,"Profit","Loss") -> Profit | T1539: 38995 | U1539: Jonathan Liebesman | V1539: 38995 | W1539: =TEXT(V1539,"MMMM") -> October | X1539: =TEXT(V1539,"YYYY") -> 2006 | Y1539: =VALUE(X1539) -> 2006 | Z1539: =TEXT(V1539,"d") -> 5 | AA1539: =VALUE(Z1539) -> 5 | AB1539: =TEXT(V1539,"dddd") -> Thursday
A1540: tt0420332 | B1540: Veer-Zaara | C1540: Veer-Zaara | D1540: 0 | E1540: 192 | F1540: =INT(E1540/60) -> 3 | G1540: =MOD(E1540,60) -> 12 | H1540: {=_xlfn.IFS(E1540<=80,"Series",E1540<=120,"TV Movie",E1540>120,"Long Movie")} -> Long Movie | I1540: Drama | J1540: Family | K1540: Musical | L1540: 7.8 | M1540: {=_xlfn.IFS(L1540<=2,"Flop",L1540<=5,"Average",L1540<=7,"Hit",L1540<=9,"Superhit",L1540>9,"BlockBuster")} -> Superhit | N1540: 56015 | O1540: {=_xlfn.IFS(N1540<=100000,"Low",N1540<=500000,"Median",N1540<=1500000,"High",N1540>1500000,"Very High")} -> Low | P1540: 7000000 | Q1540: 6887221 | R1540: =Q1540-P1540 -> -112779 | S1540: =IF(R1540>0,"Profit","Loss") -> Loss | T1540: 38303 | U1540: Yash Chopra | V1540: 38303 | W1540: =TEXT(V1540,"MMMM") -> November | X1540: =TEXT(V1540,"YYYY") -> 2004 | Y1540: =VALUE(X1540) -> 2004 | Z1540: =TEXT(V1540,"d") -> 12 | AA1540: =VALUE(Z1540) -> 12 | AB1540: =TEXT(V1540,"dddd") -> Friday
... A1627: tt0450345 | B1627: The Wicker Man | C1627: The Wicker Man | D1627: 0 | E1627: 102 | F1627: =INT(E1627/60) -> 1 | G1627: =MOD(E1627,60) -> 42 | H1627: {=_xlfn.IFS(E1627<=80,"Series",E1627<=120,"TV Movie",E1627>120,"Long Movie")} -> TV Movie | I1627: Horror | J1627: Mystery | K1627: Thriller | L1627: 3.8 | M1627: {=_xlfn.IFS(L1627<=2,"Flop",L1627<=5,"Average",L1627<=7,"Hit",L1627<=9,"Superhit",L1627>9,"BlockBuster")} -> Average | N1627: 70515 | O1627: {=_xlfn.IFS(N1627<=100000,"Low",N1627<=500000,"Median",N1627<=1500000,"High",N1627>1500000,"Very High")} -> Low | P1627: 40000000 | Q1627: 38805380 | R1627: =Q1627-P1627 -> -1194620 | S1627: =IF(R1627>0,"Profit","Loss") -> Loss | T1627: 38960 | U1627: Neil LaBute | V1627: 38960 | W1627: =TEXT(V1627,"MMMM") -> August | X1627: =TEXT(V1627,"YYYY") -> 2006 | Y1627: =VALUE(X1627) -> 2006 | Z1627: =TEXT(V1627,"d") -> 31 | AA1627: =VALUE(Z1627) -> 31 | AB1627: =TEXT(V1627,"dddd") -> Thursday
A1628: tt0450385 | B1628: 1408 | C1628: 1408 | D1628: 0 | E1628: 104 | F1628: =INT(E1628/60) -> 1 | G1628: =MOD(E1628,60) -> 44 | H1628: {=_xlfn.IFS(E1628<=80,"Series",E1628<=120,"TV Movie",E1628>120,"Long Movie")} -> TV Movie | I1628: Fantasy | J1628: Horror | K1628: Mystery | L1628: 6.8 | M1628: {=_xlfn.IFS(L1628<=2,"Flop",L1628<=5,"Average",L1628<=7,"Hit",L1628<=9,"Superhit",L1628>9,"BlockBuster")} -> Hit | N1628: 288018 | O1628: {=_xlfn.IFS(N1628<=100000,"Low",N1628<=500000,"Median",N1628<=1500000,"High",N1628>1500000,"Very High")} -> Median | P1628: 25000000 | Q1628: 132963417 | R1628: =Q1628-P1628 -> 107963417 | S1628: =IF(R1628>0,"Profit","Loss") -> Profit | T1628: 39245 | U1628: Mikael HÃ¥fstrÃ¶m | V1628: 39245 | W1628: =TEXT(V1628,"MMMM") -> June | X1628: =TEXT(V1628,"YYYY") -> 2007 | Y1628: =VALUE(X1628) -> 2007 | Z1628: =TEXT(V1628,"d") -> 12 | AA1628: =VALUE(Z1628) -> 12 | AB1628: =TEXT(V1628,"dddd") -> Tuesday
A1629: tt0451079 | B1629: Horton Hears a Who! | C1629: Horton Hears a Who! | D1629: 0 | E1629: 86 | F1629: =INT(E1629/60) -> 1 | G1629: =MOD(E1629,60) -> 26 | H1629: {=_xlfn.IFS(E1629<=80,"Series",E1629<=120,"TV Movie",E1629>120,"Long Movie")} -> TV Movie | I1629: Adventure | J1629: Animation | K1629: Comedy | L1629: 6.8 | M1629: {=_xlfn.IFS(L1629<=2,"Flop",L1629<=5,"Average",L1629<=7,"Hit",L1629<=9,"Superhit",L1629>9,"BlockBuster")} -> Hit | N1629: 147958 | O1629: {=_xlfn.IFS(N1629<=100000,"Low",N1629<=500000,"Median",N1629<=1500000,"High",N1629>1500000,"Very High")} -> Median | P1629: 85000000 | Q1629: 298572799 | R1629: =Q1629-P1629 -> 213572799 | S1629: =IF(R1629>0,"Profit","Loss") -> Profit | T1629: 39510 | U1629: Jimmy Hayward, Steve Martino | V1629: 39510 | W1629: =TEXT(V1629,"MMMM") -> March | X1629: =TEXT(V1629,"YYYY") -> 2008 | Y1629: =VALUE(X1629) -> 2008 | Z1629: =TEXT(V1629,"d") -> 3 | AA1629: =VALUE(Z1629) -> 3 | AB1629: =TEXT(V1629,"dddd") -> Monday
...

Sheet Clean Sheet
A1: id | B1: primaryTitle | C1: originalTitle | D1: isAdult | E1: runtimeMinutes | F1: Hour | G1: Minutes | H1: Runtime Classification | I1: Genres1 | J1: Genres2 | K1: Genres3 | L1: averageRating | M1: Movie Type | N1: numVotes | O1: Vote Category | P1: budget | Q1: gross | R1: Profit | S1: Profit & Loss | T1: release_date | U1: directors | V1: Release_Date | W1: Month | X1: DayName | Y1: year1 | Z1: day 1
A2: tt0035423 | B2: Kate & Leopold | C2: Kate & Leopold | D2: 0 | E2: 118 | F2: 1 | G2: 58 | H2: TV Movie | I2: Comedy | J2: Fantasy | K2: Romance | L2: 6.4 | M2: Hit | N2: 87925 | O2: Low | P2: 48000000 | Q2: 76019048 | R2: 28019048 | S2: Profit | T2: 37236 | U2: James Mangold | V2: 37236 | W2: December | X2: Tuesday | Y2: 2001 | Z2: 11
A3: tt0065421 | B3: The Aristocats | C3: The AristoCats | D3: 0 | E3: 78 | F3: 1 | G3: 18 | H3: Series | I3: Adventure | J3: Animation | K3: Comedy | L3: 7.1 | M3: Superhit | N3: 111758 | O3: Median | P3: 4000000 | Q3: 35459543 | R3: 31459543 | S3: Profit | T3: 25913 | U3: Wolfgang Reitherman | V3: 25913 | W3: December | X3: Friday | Y3: 1970 | Z3: 11
A4: tt0065938 | B4: Kelly's Heroes | C4: Kelly's Heroes | D4: 0 | E4: 144 | F4: 2 | G4: 24 | H4: Long Movie | I4: Adventure | J4: Comedy | K4: War | L4: 7.6 | M4: Superhit | N4: 52628 | O4: Low | P4: 4000000 | Q4: 5200000 | R4: 1200000 | S4: Profit | T4: 25569 | U4: Brian G. Hutton | V4: 25569 | W4: January | X4: Thursday | Y4: 1970 | Z4: 1
A5: tt0066026 | B5: M*A*S*H | C5: M*A*S*H | D5: 0 | E5: 116 | F5: 1 | G5: 56 | H5: TV Movie | I5: Comedy | J5: Drama | K5: War | L5: 7.4 | M5: Superhit | N5: 75784 | O5: Low | P5: 3500000 | Q5: 81600000 | R5: 78100000 | S5: Profit | T5: 25593 | U5: Robert Altman | V5: 25593 | W5: January | X5: Sunday | Y5: 1970 | Z5: 25
A6: tt0066206 | B6: Patton | C6: Patton | D6: 0 | E6: 172 | F6: 2 | G6: 52 | H6: Long Movie | I6: Biography | J6: Drama | K6: War | L6: 7.9 | M6: Superhit | N6: 106476 | O6: Median | P6: 12000000 | Q6: 61749765 | R6: 49749765 | S6: Profit | T6: 25603 | U6: Franklin J. Schaffner | V6: 25603 | W6: February | X6: Wednesday | Y6: 1970 | Z6: 4
A7: tt0066434 | B7: THX 1138 | C7: THX 1138 | D7: 0 | E7: 86 | F7: 1 | G7: 26 | H7: TV Movie | I7: Drama | J7: Sci-Fi | K7: Thriller | L7: 6.6 | M7: Hit | N7: 53906 | O7: Low | P7: 777000 | Q7: 2437000 | R7: 1660000 | S7: Profit | T7: 26003 | U7: George Lucas | V7: 26003 | W7: March | X7: Thursday | Y7: 1971 | Z7: 11
A8: tt0066921 | B8: A Clockwork Orange | C8: A Clockwork Orange | D8: 0 | E8: 136 | F8: 2 | G8: 16 | H8: Long Movie | I8: Crime | J8: Sci-Fi | K8: Unknown | L8: 8.3 | M8: Superhit | N8: 864440 | O8: High | P8: 2200000 | Q8: 26960374 | R8: 24760374 | S8: Profit | T8: 26286 | U8: Stanley Kubrick | V8: 26286 | W8: December | X8: Sunday | Y8: 1971 | Z8: 19
A9: tt0066995 | B9: Diamonds Are Forever | C9: Diamonds Are Forever | D9: 0 | E9: 120 | F9: 2 | G9: 0 | H9: TV Movie | I9: Action | J9: Adventure | K9: Thriller | L9: 6.5 | M9: Hit | N9: 112043 | O9: Median | P9: 7200000 | Q9: 43829933 | R9: 36629933 | S9: Profit | T9: 26281 | U9: Guy Hamilton | V9: 26281 | W9: December | X9: Tuesday | Y9: 1971 | Z9: 14
A10: tt0066999 | B10: Dirty Harry | C10: Dirty Harry | D10: 0 | E10: 102 | F10: 1 | G10: 42 | H10: TV Movie | I10: Action | J10: Crime | K10: Thriller | L10: 7.7 | M10: Superhit | N10: 165277 | O10: Median | P10: 4000000 | Q10: 35988495 | R10: 31988495 | S10: Profit | T10: 26288 | U10: Don Siegel, Clint Eastwood | V10: 26288 | W10: December | X10: Tuesday | Y10: 1971 | Z10: 21
A11: tt0067116 | B11: The French Connection | C11: The French Connection | D11: 0 | E11: 104 | F11: 1 | G11: 44 | H11: TV Movie | I11: Action | J11: Crime | K11: Drama | L11: 7.7 | M11: Superhit | N11: 131995 | O11: Median | P11: 1800000 | Q11: 51701871 | R11: 49901871 | S11: Profit | T11: 26213 | U11: William Friedkin | V11: 26213 | W11: October | X11: Thursday | Y11: 1971 | Z11: 7
A12: tt0067185 | B12: Harold and Maude | C12: Harold and Maude | D12: 0 | E12: 91 | F12: 1 | G12: 31 | H12: TV Movie | I12: Comedy | J12: Drama | K12: Romance | L12: 7.9 | M12: Superhit | N12: 80626 | O12: Low | P12: 1200000 | Q12: 1546 | R12: -1198454 | S12: Loss | T12: 26287 | U12: Hal Ashby | V12: 26287 | W12: December | X12: Monday | Y12: 1971 | Z12: 20
A13: tt0067328 | B13: The Last Picture Show | C13: The Last Picture Show | D13: 0 | E13: 118 | F13: 1 | G13: 58 | H13: TV Movie | I13: Drama | J13: Romance | K13: Unknown | L13: 8 | M13: Superhit | N13: 51275 | O13: Low | P13: 1300000 | Q13: 29146131 | R13: 27846131 | S13: Profit | T13: 26208 | U13: Peter Bogdanovich | V13: 26208 | W13: October | X13: Saturday | Y13: 1971 | Z13: 2
... A466: tt0106977 | B466: The Fugitive | C466: The Fugitive | D466: 0 | E466: 130 | F466: 2 | G466: 10 | H466: Long Movie | I466: Action | J466: Crime | K466: Drama | L466: 7.8 | M466: Superhit | N466: 310966 | O466: Median | P466: 44000000 | Q466: 368875760 | R466: 324875760 | S466: Profit | T466: 34179 | U466: Andrew Davis | V466: 34179 | W466: July | X466: Thursday | Y466: 1993 | Z466: 29
A467: tt0107048 | B467: Groundhog Day | C467: Groundhog Day | D467: 0 | E467: 101 | F467: 1 | G467: 41 | H467: TV Movie | I467: Comedy | J467: Drama | K467: Fantasy | L467: 8 | M467: Superhit | N467: 666512 | O467: High | P467: 14600000 | Q467: 71108591 | R467: 56508591 | S467: Profit | T467: NA | U467: Harold Ramis | V467: NA | W467: NA | X467: NA | Y467: #VALUE! | Z467: #VALUE!
A468: tt0107076 | B468: Hard Target | C468: Hard Target | D468: 0 | E468: 97 | F468: 1 | G468: 37 | H468: TV Movie | I468: Action | J468: Crime | K468: Thriller | L468: 6.2 | M468: Hit | N468: 54931 | O468: Low | P468: 18000000 | Q468: 74189677 | R468: 56189677 | S468: Profit | T468: 34201 | U468: John Woo | V468: 34201 | W468: August | X468: Friday | Y468: 1993 | Z468: 20
A469: tt0107120 | B469: Hocus Pocus | C469: Hocus Pocus | D469: 0 | E469: 96 | F469: 1 | G469: 36 | H469: TV Movie | I469: Comedy | J469: Family | K469: Fantasy | L469: 6.9 | M469: Hit | N469: 153494 | O469: Median | P469: 28000000 | Q469: 50789441 | R469: 22789441 | S469: Profit | T469: 34160 | U469: Kenny Ortega | V469: 34160 | W469: July | X469: Saturday | Y469: 1993 | Z469: 10
A470: tt0107144 | B470: Hot Shots! Part Deux | C470: Hot Shots! Part Deux | D470: 0 | E470: 86 | F470: 1 | G470: 26 | H470: TV Movie | I470: Action | J470: Comedy | K470: Unknown | L470: 6.6 | M470: Hit | N470: 95577 | O470: Low | P470: 25000000 | Q470: 133752825 | R470: 108752825 | S470: Profit | T470: 34110 | U470: Jim Abrahams | V470: 34110 | W470: May | X470: Friday | Y470: 1993 | Z470: 21
A471: tt0107206 | B471: In the Line of Fire | C471: In the Line of Fire | D471: 0 | E471: 128 | F471: 2 | G471: 8 | H471: Long Movie | I471: Action | J471: Crime | K471: Drama | L471: 7.2 | M471: Superhit | N471: 111126 | O471: Median | P471: 40000000 | Q471: 176997168 | R471: 136997168 | S471: Profit | T471: 34158 | U471: Wolfgang Petersen | V471: 34158 | W471: July | X471: Thursday | Y471: 1993 | Z471: 8
A472: tt0107207 | B472: In the Name of the Father | C472: In the Name of the Father | D472: 0 | E472: 133 | F472: 2 | G472: 13 | H472: Long Movie | I472: Biography | J472: Crime | K472: Drama | L472: 8.1 | M472: Superhit | N472: 183546 | O472: Median | P472: 13000000 | Q472: 65796862 | R472: 52796862 | S472: Profit | T472: 34315 | U472: Jim Sheridan | V472: 34315 | W472: December | X472: Sunday | Y472: 1993 | Z472: 12
A473: tt0107211 | B473: Indecent Proposal | C473: Indecent Proposal | D473: 0 | E473: 117 | F473: 1 | G473: 57 | H473: TV Movie | I473: Drama | J473: Romance | K473: Unknown | L473: 6 | M473: Hit | N473: 76245 | O473: Low | P473: 38000000 | Q473: 266614059 | R473: 228614059 | S473: Profit | T473: 34065 | U473: Adrian Lyne | V473: 34065 | W473: April | X473: Tuesday | Y473: 1993 | Z473: 6
A474: tt0107290 | B474: Jurassic Park | C474: Jurassic Park | D474: 0 | E474: 127 | F474: 2 | G474: 7 | H474: Long Movie | I474: Action | J474: Adventure | K474: Sci-Fi | L474: 8.2 | M474: Superhit | N474: 1041089 | O474: High | P474: 63000000 | Q474: 1113138548 | R474: 1050138548 | S474: Profit | T474: 34129 | U474: Steven Spielberg | V474: 34129 | W474: June | X474: Wednesday | Y474: 1993 | Z474: 9
A475: tt0107302 | B475: Kalifornia | C475: Kalifornia | D475: 0 | E475: 117 | F475: 1 | G475: 57 | H475: TV Movie | I475: Crime | J475: Drama | K475: Thriller | L475: 6.7 | M475: Hit | N475: 56797 | O475: Low | P475: 9000000 | Q475: 2395231 | R475: -6604769 | S475: Loss | T475: 34182 | U475: Dominic Sena | V475: 34182 | W475: August | X475: Sunday | Y475: 1993 | Z475: 1
A476: tt0107362 | B476: Last Action Hero | C476: Last Action Hero | D476: 0 | E476: 130 | F476: 2 | G476: 10 | H476: Long Movie | I476: Action | J476: Adventure | K476: Comedy | L476: 6.5 | M476: Hit | N476: 160479 | O476: Median | P476: 85000000 | Q476: 137298489 | R476: 52298489 | S476: Profit | T476: 34133 | U476: John McTiernan | V476: 34133 | W476: June | X476: Sunday | Y476: 1993 | Z476: 13
A477: tt0107554 | B477: Menace II Society | C477: Menace II Society | D477: 0 | E477: 97 | F477: 1 | G477: 37 | H477: TV Movie | I477: Crime | J477: Drama | K477: Thriller | L477: 7.5 | M477: Superhit | N477: 63036 | O477: Low | P477: 3500000 | Q477: 27912072 | R477: 24412072 | S477: Profit | T477: 34115 | U477: Albert Hughes, Allen Hughes | V477: 34115 | W477: May | X477: Wednesday | Y477: 1993 | Z477: 26
A478: tt0107614 | B478: Mrs. Doubtfire | C478: Mrs. Doubtfire | D478: 0 | E478: 125 | F478: 2 | G478: 5 | H478: Long Movie | I478: Comedy | J478: Drama | K478: Unknown | L478: 7.1 | M478: Superhit | N478: 283743 | O478: Median | P478: 25000000 | Q478: 441286195 | R478: 416286195 | S478: Profit | T478: 34295 | U478: Chris Columbus | V478: 34295 | W478: November | X478: Monday | Y478: 1993 | Z478: 22
A479: tt0107616 | B479: Much Ado About Nothing | C479: Much Ado About Nothing | D479: 0 | E479: 111 | F479: 1 | G479: 51 | H479: TV Movie | I479: Comedy | J479: Drama | K479: Romance | L479: 7.3 | M479: Superhit | N479: 50854 | O479: Low | P479: 11000000 | Q479: 22549338 | R479: 11549338 | S479: Profit | T479: 34095 | U479: Kenneth Branagh | V479: 34095 | W479: May | X479: Thursday | Y479: 1993 | Z479: 6
... A525: tt0110912 | B525: Pulp Fiction | C525: Pulp Fiction | D525: 0 | E525: 154 | F525: 2 | G525: 34 | H525: Long Movie | I525: Crime | J525: Drama | K525: Unknown | L525: 8.9 | M525: Superhit | N525: 2160463 | O525: Very High | P525: 8000000 | Q525: 213928762 | R525: 205928762 | S525: Profit | T525: 34475 | U525: Quentin Tarantino | V525: 34475 | W525: May | X525: Saturday | Y525: 1994 | Z525: 21
A526: tt0110932 | B526: Quiz Show | C526: Quiz Show | D526: 0 | E526: 133 | F526: 2 | G526: 13 | H526: Long Movie | I526: Biography | J526: Drama | K526: History | L526: 7.5 | M526: Superhit | N526: 72316 | O526: Low | P526: 31000000 | Q526: 24822619 | R526: -6177381 | S526: Loss | T526: NA | U526: Robert Redford | V526: NA | W526: NA | X526: NA | Y526: #VALUE! | Z526: #VALUE!
A527: tt0110950 | B527: Reality Bites | C527: Reality Bites | D527: 0 | E527: 99 | F527: 1 | G527: 39 | H527: TV Movie | I527: Comedy | J527: Drama | K527: Romance | L527: 6.6 | M527: Hit | N527: 52717 | O527: Low | P527: 11500000 | Q527: 33351557 | R527: 21851557 | S527: Profit | T527: 34335 | U527: Ben Stiller | V527: 34335 | W527: January | X527: Saturday | Y527: 1994 | Z527: 1
A528: tt0110989 | B528: Richie Rich | C528: RiÂ¢hie RiÂ¢h | D528: 0 | E528: 95 | F528: 1 | G528: 35 | H528: TV Movie | I528: Comedy | J528: Family | K528: Unknown | L528: 5.4 | M528: Hit | N528: 72205 | O528: Low | P528: 40000000 | Q528: 38087756 | R528: -1912244 | S528: Loss | T528: 34687 | U528: Donald Petrie | V528: 34687 | W528: December | X528: Monday | Y528: 1994 | Z528: 19
A529: tt0111070 | B529: The Santa Clause | C529: The Santa Clause | D529: 0 | E529: 97 | F529: 1 | G529: 37 | H529: TV Movie | I529: Comedy | J529: Drama | K529: Family | L529: 6.5 | M529: Hit | N529: 126968 | O529: Median | P529: 22000000 | Q529: 190539357 | R529: 168539357 | S529: Profit | T529: 34649 | U529: John Pasquin | V529: 34649 | W529: November | X529: Friday | Y529: 1994 | Z529: 11
A530: tt0111149 | B530: Shallow Grave | C530: Shallow Grave | D530: 0 | E530: 89 | F530: 1 | G530: 29 | H530: TV Movie | I530: Crime | J530: Drama | K530: Thriller | L530: 7.3 | M530: Superhit | N530: 65075 | O530: Low | P530: 2500000 | Q530: 2079569 | R530: -420431 | S530: Loss | T530: 34471 | U530: Danny Boyle | V530: 34471 | W530: May | X530: Tuesday | Y530: 1994 | Z530: 17
A531: tt0111161 | B531: The Shawshank Redemption | C531: The Shawshank Redemption | D531: 0 | E531: 142 | F531: 2 | G531: 22 | H531: Long Movie | I531: Drama | J531: Unknown | K531: Unknown | L531: 9.3 | M531: BlockBuster | N531: 2817283 | O531: Very High | P531: 25000000 | Q531: 28884716 | R531: 3884716 | S531: Profit | T531: 34587 | U531: Frank Darabont | V531: 34587 | W531: September | X531: Saturday | Y531: 1994 | Z531: 10
A532: tt0111255 | B532: The Specialist | C532: The Specialist | D532: 0 | E532: 110 | F532: 1 | G532: 50 | H532: TV Movie | I532: Action | J532: Drama | K532: Thriller | L532: 5.6 | M532: Hit | N532: 68821 | O532: Low | P532: 45000000 | Q532: 170362582 | R532: 125362582 | S532: Profit | T532: 34614 | U532: Luis Llosa | V532: 34614 | W532: October | X532: Friday | Y532: 1994 | Z532: 7
A533: tt0111257 | B533: Speed | C533: Speed | D533: 0 | E533: 116 | F533: 1 | G533: 56 | H533: TV Movie | I533: Action | J533: Adventure | K533: Thriller | L533: 7.3 | M533: Superhit | N533: 383702 | O533: Median | P533: 30000000 | Q533: 350448145 | R533: 320448145 | S533: Profit | T533: 34492 | U533: Jan de Bont | V533: 34492 | W533: June | X533: Tuesday | Y533: 1994 | Z533: 7
A534: tt0111280 | B534: Star Trek: Generations | C534: Star Trek: Generations | D534: 0 | E534: 118 | F534: 1 | G534: 58 | H534: TV Movie | I534: Action | J534: Adventure | K534: Mystery | L534: 6.6 | M534: Hit | N534: 85822 | O534: Low | P534: 35000000 | Q534: 118071125 | R534: 83071125 | S534: Profit | T534: 34655 | U534: David Carson | V534: 34655 | W534: November | X534: Thursday | Y534: 1994 | Z534: 17
A535: tt0111282 | B535: Stargate | C535: Stargate | D535: 0 | E535: 116 | F535: 1 | G535: 56 | H535: TV Movie | I535: Action | J535: Adventure | K535: Sci-Fi | L535: 7 | M535: Hit | N535: 200994 | O535: Median | P535: 55000000 | Q535: 196567262 | R535: 141567262 | S535: Profit | T535: 34635 | U535: Roland Emmerich | V535: 34635 | W535: October | X535: Friday | Y535: 1994 | Z535: 28
A536: tt0111301 | B536: Street Fighter | C536: Street Fighter | D536: 0 | E536: 102 | F536: 1 | G536: 42 | H536: TV Movie | I536: Action | J536: Adventure | K536: Comedy | L536: 4 | M536: Average | N536: 74256 | O536: Low | P536: 35000000 | Q536: 99431786 | R536: 64431786 | S536: Profit | T536: 34691 | U536: Steven E. de Souza | V536: 34691 | W536: December | X536: Friday | Y536: 1994 | Z536: 23
A537: tt0111438 | B537: Timecop | C537: Timecop | D537: 0 | E537: 99 | F537: 1 | G537: 39 | H537: TV Movie | I537: Action | J537: Crime | K537: Sci-Fi | L537: 5.9 | M537: Hit | N537: 62760 | O537: Low | P537: 27000000 | Q537: 101646581 | R537: 74646581 | S537: Profit | T537: 34593 | U537: Peter Hyams | V537: 34593 | W537: September | X537: Friday | Y537: 1994 | Z537: 16
A538: tt0111503 | B538: True Lies | C538: True Lies | D538: 0 | E538: 141 | F538: 2 | G538: 21 | H538: Long Movie | I538: Action | J538: Comedy | K538: Thriller | L538: 7.3 | M538: Superhit | N538: 274856 | O538: Median | P538: 115000000 | Q538: 378882411 | R538: 263882411 | S538: Profit | T538: 34527 | U538: James Cameron | V538: 34527 | W538: July | X538: Tuesday | Y538: 1994 | Z538: 12
... A987: tt0212346 | B987: Miss Congeniality | C987: Miss Congeniality | D987: 0 | E987: 109 | F987: 1 | G987: 49 | H987: TV Movie | I987: Action | J987: Comedy | K987: Crime | L987: 6.3 | M987: Hit | N987: 224537 | O987: Median | P987: 45000000 | Q987: 212742720 | R987: 167742720 | S987: Profit | T987: 36874 | U987: Donald Petrie | V987: 36874 | W987: December | X987: Thursday | Y987: 2000 | Z987: 14
A988: tt0212712 | B988: 2046 | C988: 2046 | D988: 0 | E988: 129 | F988: 2 | G988: 9 | H988: Long Movie | I988: Drama | J988: Romance | K988: Sci-Fi | L988: 7.4 | M988: Superhit | N988: 60667 | O988: Low | P988: 12000000 | Q988: 20205757 | R988: 8205757 | S988: Profit | T988: 38127 | U988: Kar-Wai Wong | V988: 38127 | W988: May | X988: Thursday | Y988: 2004 | Z988: 20
A989: tt0212720 | B989: A.I. Artificial Intelligence | C989: A.I. Artificial Intelligence | D989: 0 | E989: 146 | F989: 2 | G989: 26 | H989: Long Movie | I989: Drama | J989: Sci-Fi | K989: Unknown | L989: 7.2 | M989: Superhit | N989: 318645 | O989: Median | P989: 100000000 | Q989: 235926552 | R989: 135926552 | S989: Profit | T989: 37068 | U989: Steven Spielberg | V989: 37068 | W989: June | X989: Tuesday | Y989: 2001 | Z989: 26
A990: tt0212985 | B990: Hannibal | C990: Hannibal | D990: 0 | E990: 131 | F990: 2 | G990: 11 | H990: Long Movie | I990: Crime | J990: Drama | K990: Thriller | L990: 6.8 | M990: Hit | N990: 287505 | O990: Median | P990: 87000000 | Q990: 351692268 | R990: 264692268 | S990: Profit | T990: 36931 | U990: Ridley Scott | V990: 36931 | W990: February | X990: Friday | Y990: 2001 | Z990: 9
A991: tt0213149 | B991: Pearl Harbor | C991: Pearl Harbor | D991: 0 | E991: 183 | F991: 3 | G991: 3 | H991: Long Movie | I991: Action | J991: Drama | K991: History | L991: 6.2 | M991: Hit | N991: 346541 | O991: Median | P991: 140000000 | Q991: 449220945 | R991: 309220945 | S991: Profit | T991: 37032 | U991: Michael Bay | V991: 37032 | W991: May | X991: Monday | Y991: 2001 | Z991: 21
A992: tt0215129 | B992: Road Trip | C992: Road Trip | D992: 0 | E992: 93 | F992: 1 | G992: 33 | H992: TV Movie | I992: Comedy | J992: Unknown | K992: Unknown | L992: 6.5 | M992: Hit | N992: 175502 | O992: Median | P992: 16000000 | Q992: 119754278 | R992: 103754278 | S992: Profit | T992: 36657 | U992: Todd Phillips | V992: 36657 | W992: May | X992: Thursday | Y992: 2000 | Z992: 11
A993: tt0215750 | B993: Enemy at the Gates | C993: Enemy at the Gates | D993: 0 | E993: 131 | F993: 2 | G993: 11 | H993: Long Movie | I993: Action | J993: Drama | K993: War | L993: 7.5 | M993: Superhit | N993: 273308 | O993: Median | P993: 68000000 | Q993: 96976270 | R993: 28976270 | S993: Profit | T993: 36929 | U993: Jean-Jacques Annaud | V993: 36929 | W993: February | X993: Wednesday | Y993: 2001 | Z993: 7
A994: tt0216216 | B994: The 6th Day | C994: The 6th Day | D994: 0 | E994: 123 | F994: 2 | G994: 3 | H994: Long Movie | I994: Action | J994: Mystery | K994: Sci-Fi | L994: 5.9 | M994: Hit | N994: 126471 | O994: Median | P994: 82000000 | Q994: 96085477 | R994: 14085477 | S994: Profit | T994: 36827 | U994: Roger Spottiswoode | V994: 36827 | W994: October | X994: Saturday | Y994: 2000 | Z994: 28
A995: tt0217505 | B995: Gangs of New York | C995: Gangs of New York | D995: 0 | E995: 167 | F995: 2 | G995: 47 | H995: Long Movie | I995: Crime | J995: Drama | K995: Unknown | L995: 7.5 | M995: Superhit | N995: 463841 | O995: Median | P995: 100000000 | Q995: 193772504 | R995: 93772504 | S995: Profit | T995: 37599 | U995: Martin Scorsese | V995: 37599 | W995: December | X995: Monday | Y995: 2002 | Z995: 9
A996: tt0217869 | B996: Unbreakable | C996: Unbreakable | D996: 0 | E996: 106 | F996: 1 | G996: 46 | H996: TV Movie | I996: Drama | J996: Mystery | K996: Sci-Fi | L996: 7.3 | M996: Superhit | N996: 434233 | O996: Median | P996: 75000000 | Q996: 248118121 | R996: 173118121 | S996: Profit | T996: 36844 | U996: M. Night Shyamalan | V996: 36844 | W996: November | X996: Tuesday | Y996: 2000 | Z996: 14
A997: tt0218839 | B997: Best in Show | C997: Best in Show | D997: 0 | E997: 90 | F997: 1 | G997: 30 | H997: TV Movie | I997: Comedy | J997: Unknown | K997: Unknown | L997: 7.4 | M997: Superhit | N997: 65456 | O997: Low | P997: 10000000 | Q997: 20789556 | R997: 10789556 | S997: Profit | T997: 36777 | U997: Christopher Guest | V997: 36777 | W997: September | X997: Friday | Y997: 2000 | Z997: 8
A998: tt0218922 | B998: Original Sin | C998: Original Sin | D998: 0 | E998: 116 | F998: 1 | G998: 56 | H998: TV Movie | I998: Drama | J998: Mystery | K998: Romance | L998: 6 | M998: Hit | N998: 58920 | O998: Low | P998: 42000000 | Q998: 35402320 | R998: -6597680 | S998: Loss | T998: 37083 | U998: Michael Cristofer | V998: 37083 | W998: July | X998: Wednesday | Y998: 2001 | Z998: 11
A999: tt0218967 | B999: The Family Man | C999: The Family Man | D999: 0 | E999: 125 | F999: 2 | G999: 5 | H999: Long Movie | I999: Comedy | J999: Drama | K999: Fantasy | L999: 6.8 | M999: Hit | N999: 115632 | O999: Median | P999: 60000000 | Q999: 124745083 | R999: 64745083 | S999: Profit | T999: 36872 | U999: Brett Ratner | V999: 36872 | W999: December | X999: Tuesday | Y999: 2000 | Z999: 12
A1000: tt0219699 | B1000: The Gift | C1000: The Gift | D1000: 0 | E1000: 112 | F1000: 1 | G1000: 52 | H1000: TV Movie | I1000: Drama | J1000: Fantasy | K1000: Horror | L1000: 6.7 | M1000: Hit | N1000: 73540 | O1000: Low | P1000: 10000000 | Q1000: 44567606 | R1000: 34567606 | S1000: Profit | T1000: 36878 | U1000: Sam Raimi | V1000: 36878 | W1000: December | X1000: Monday | Y1000: 2000 | Z1000: 18
... A1191: tt0306047 | B1191: Scary Movie 3 | C1191: Scary Movie 3 | D1191: 0 | E1191: 84 | F1191: 1 | G1191: 24 | H1191: TV Movie | I1191: Comedy | J1191: Unknown | K1191: Unknown | L1191: 5.5 | M1191: Hit | N1191: 155399 | O1191: Median | P1191: 48000000 | Q1191: 220673217 | R1191: 172673217 | S1191: Profit | T1191: 37914 | U1191: David Zucker | V1191: 37914 | W1191: October | X1191: Monday | Y1191: 2003 | Z1191: 20
A1192: tt0307453 | B1192: Shark Tale | C1192: Shark Tale | D1192: 0 | E1192: 90 | F1192: 1 | G1192: 30 | H1192: TV Movie | I1192: Adventure | J1192: Animation | K1192: Comedy | L1192: 6 | M1192: Hit | N1192: 194771 | O1192: Median | P1192: 75000000 | Q1192: 374583879 | R1192: 299583879 | S1192: Profit | T1192: NA | U1192: Bibo Bergeron, Vicky Jenson, Rob Letterman | V1192: NA | W1192: NA | X1192: NA | Y1192: #VALUE! | Z1192: #VALUE!
A1193: tt0307479 | B1193: Solaris | C1193: Solaris | D1193: 0 | E1193: 99 | F1193: 1 | G1193: 39 | H1193: TV Movie | I1193: Drama | J1193: Mystery | K1193: Romance | L1193: 6.2 | M1193: Hit | N1193: 85320 | O1193: Low | P1193: 47000000 | Q1193: 30002758 | R1193: -16997242 | S1193: Loss | T1193: 37579 | U1193: Steven Soderbergh | V1193: 37579 | W1193: November | X1193: Tuesday | Y1193: 2002 | Z1193: 19
A1194: tt0307901 | B1194: 25th Hour | C1194: 25th Hour | D1194: 0 | E1194: 135 | F1194: 2 | G1194: 15 | H1194: Long Movie | I1194: Drama | J1194: Unknown | K1194: Unknown | L1194: 7.6 | M1194: Superhit | N1194: 183164 | O1194: Median | P1194: 5000000 | Q1194: 23932055 | R1194: 18932055 | S1194: Profit | T1194: 37606 | U1194: Spike Lee | V1194: 37606 | W1194: December | X1194: Monday | Y1194: 2002 | Z1194: 16
A1195: tt0307987 | B1195: Bad Santa | C1195: Bad Santa | D1195: 0 | E1195: 92 | F1195: 1 | G1195: 32 | H1195: TV Movie | I1195: Comedy | J1195: Crime | K1195: Drama | L1195: 7.1 | M1195: Superhit | N1195: 150117 | O1195: Median | P1195: 23000000 | Q1195: 76490720 | R1195: 53490720 | S1195: Profit | T1195: 37943 | U1195: Terry Zwigoff | V1195: 37943 | W1195: November | X1195: Tuesday | Y1195: 2003 | Z1195: 18
A1196: tt0308644 | B1196: Finding Neverland | C1196: Finding Neverland | D1196: 0 | E1196: 106 | F1196: 1 | G1196: 46 | H1196: TV Movie | I1196: Biography | J1196: Drama | K1196: Family | L1196: 7.7 | M1196: Superhit | N1196: 210506 | O1196: Median | P1196: 25000000 | Q1196: 116650613 | R1196: 91650613 | S1196: Profit | T1196: 38234 | U1196: Marc Forster | V1196: 38234 | W1196: September | X1196: Saturday | Y1196: 2004 | Z1196: 4
A1197: tt0309593 | B1197: Final Destination 2 | C1197: Final Destination 2 | D1197: 0 | E1197: 90 | F1197: 1 | G1197: 30 | H1197: TV Movie | I1197: Horror | J1197: Thriller | K1197: Unknown | L1197: 6.2 | M1197: Hit | N1197: 178305 | O1197: Median | P1197: 26000000 | Q1197: 90941129 | R1197: 64941129 | S1197: Profit | T1197: 37651 | U1197: David R. Ellis | V1197: 37651 | W1197: January | X1197: Thursday | Y1197: 2003 | Z1197: 30
A1198: tt0309698 | B1198: Identity | C1198: Identity | D1198: 0 | E1198: 90 | F1198: 1 | G1198: 30 | H1198: TV Movie | I1198: Mystery | J1198: Thriller | K1198: Unknown | L1198: 7.3 | M1198: Superhit | N1198: 262068 | O1198: Median | P1198: 28000000 | Q1198: 90259536 | R1198: 62259536 | S1198: Profit | T1198: 37734 | U1198: James Mangold | V1198: 37734 | W1198: April | X1198: Wednesday | Y1198: 2003 | Z1198: 23
A1199: tt0309987 | B1199: The Dreamers | C1199: The Dreamers | D1199: 0 | E1199: 115 | F1199: 1 | G1199: 55 | H1199: TV Movie | I1199: Drama | J1199: Romance | K1199: Unknown | L1199: 7.1 | M1199: Superhit | N1199: 128480 | O1199: Median | P1199: 15000000 | Q1199: 24152155 | R1199: 9152155 | S1199: Profit | T1199: 37865 | U1199: Bernardo Bertolucci | V1199: 37865 | W1199: September | X1199: Monday | Y1199: 2003 | Z1199: 1
A1200: tt0310775 | B1200: Sympathy for Mr. Vengeance | C1200: Boksuneun naui geot | D1200: 0 | E1200: 129 | F1200: 2 | G1200: 9 | H1200: Long Movie | I1200: Crime | J1200: Drama | K1200: Thriller | L1200: 7.5 | M1200: Superhit | N1200: 73577 | O1200: Low | P1200: 4000000 | Q1200: 2046061 | R1200: -1953939 | S1200: Loss | T1200: 37344 | U1200: Park Chan-wook | V1200: 37344 | W1200: March | X1200: Friday | Y1200: 2002 | Z1200: 29
A1201: tt0310793 | B1201: Bowling for Columbine | C1201: Bowling for Columbine | D1201: 0 | E1201: 120 | F1201: 2 | G1201: 0 | H1201: TV Movie | I1201: Crime | J1201: Documentary | K1201: Drama | L1201: 8 | M1201: Superhit | N1201: 147608 | O1201: Median | P1201: 4000000 | Q1201: 58011975 | R1201: 54011975 | S1201: Profit | T1201: 37392 | U1201: Michael Moore | V1201: 37392 | W1201: May | X1201: Thursday | Y1201: 2002 | Z1201: 16
A1202: tt0311113 | B1202: Master and Commander: The Far Side of the World | C1202: Master and Commander: The Far Side of the World | D1202: 0 | E1202: 138 | F1202: 2 | G1202: 18 | H1202: Long Movie | I1202: Action | J1202: Adventure | K1202: Drama | L1202: 7.5 | M1202: Superhit | N1202: 232865 | O1202: Median | P1202: 150000000 | Q1202: 211622535 | R1202: 61622535 | S1202: Profit | T1202: 37936 | U1202: Peter Weir | V1202: 37936 | W1202: November | X1202: Tuesday | Y1202: 2003 | Z1202: 11
A1203: tt0311289 | B1203: Holes | C1203: Holes | D1203: 0 | E1203: 117 | F1203: 1 | G1203: 57 | H1203: TV Movie | I1203: Adventure | J1203: Comedy | K1203: Drama | L1203: 7 | M1203: Hit | N1203: 97228 | O1203: Low | P1203: 20000000 | Q1203: 71406573 | R1203: 51406573 | S1203: Profit | T1203: 37722 | U1203: Andrew Davis | V1203: 37722 | W1203: April | X1203: Friday | Y1203: 2003 | Z1203: 11
A1204: tt0311429 | B1204: The League of Extraordinary Gentlemen | C1204: The League of Extraordinary Gentlemen | D1204: 0 | E1204: 110 | F1204: 1 | G1204: 50 | H1204: TV Movie | I1204: Action | J1204: Adventure | K1204: Fantasy | L1204: 5.8 | M1204: Hit | N1204: 181832 | O1204: Median | P1204: 78000000 | Q1204: 179265204 | R1204: 101265204 | S1204: Profit | T1204: 37813 | U1204: Stephen Norrington | V1204: 37813 | W1204: July | X1204: Friday | Y1204: 2003 | Z1204: 11
... A1299: tt0348150 | B1299: Superman Returns | C1299: Superman Returns | D1299: 0 | E1299: 154 | F1299: 2 | G1299: 34 | H1299: Long Movie | I1299: Action | J1299: Adventure | K1299: Sci-Fi | L1299: 6.1 | M1299: Hit | N1299: 289349 | O1299: Median | P1299: 270000000 | Q1299: 391081192 | R1299: 121081192 | S1299: Profit | T1299: 38889 | U1299: Bryan Singer | V1299: 38889 | W1299: June | X1299: Wednesday | Y1299: 2006 | Z1299: 21
A1300: tt0348333 | B1300: Waiting... | C1300: Waiting... | D1300: 0 | E1300: 94 | F1300: 1 | G1300: 34 | H1300: TV Movie | I1300: Comedy | J1300: Unknown | K1300: Unknown | L1300: 6.7 | M1300: Hit | N1300: 103903 | O1300: Median | P1300: 3000000 | Q1300: 18637690 | R1300: 15637690 | S1300: Profit | T1300: NA | U1300: Rob McKittrick | V1300: NA | W1300: NA | X1300: NA | Y1300: #VALUE! | Z1300: #VALUE!
A1301: tt0348836 | B1301: Gothika | C1301: Gothika | D1301: 0 | E1301: 98 | F1301: 1 | G1301: 38 | H1301: TV Movie | I1301: Horror | J1301: Mystery | K1301: Thriller | L1301: 5.8 | M1301: Hit | N1301: 117496 | O1301: Median | P1301: 40000000 | Q1301: 141591324 | R1301: 101591324 | S1301: Profit | T1301: 37938 | U1301: Mathieu Kassovitz | V1301: 37938 | W1301: November | X1301: Thursday | Y1301: 2003 | Z1301: 13
A1302: tt0349205 | B1302: Cheaper by the Dozen | C1302: Cheaper by the Dozen | D1302: 0 | E1302: 98 | F1302: 1 | G1302: 38 | H1302: TV Movie | I1302: Comedy | J1302: Family | K1302: Unknown | L1302: 5.9 | M1302: Hit | N1302: 107166 | O1302: Median | P1302: 40000000 | Q1302: 190538630 | R1302: 150538630 | S1302: Profit | T1302: 37947 | U1302: Shawn Levy | V1302: 37947 | W1302: November | X1302: Saturday | Y1302: 2003 | Z1302: 22
A1303: tt0349683 | B1303: King Arthur | C1303: King Arthur | D1303: 0 | E1303: 126 | F1303: 2 | G1303: 6 | H1303: Long Movie | I1303: Action | J1303: Adventure | K1303: Drama | L1303: 6.3 | M1303: Hit | N1303: 173873 | O1303: Median | P1303: 120000000 | Q1303: 203567857 | R1303: 83567857 | S1303: Profit | T1303: 38166 | U1303: Antoine Fuqua | V1303: 38166 | W1303: June | X1303: Monday | Y1303: 2004 | Z1303: 28
A1304: tt0349710 | B1304: Ladder 49 | C1304: Ladder 49 | D1304: 0 | E1304: 115 | F1304: 1 | G1304: 55 | H1304: TV Movie | I1304: Action | J1304: Drama | K1304: Thriller | L1304: 6.5 | M1304: Hit | N1304: 58971 | O1304: Low | P1304: 45000000 | Q1304: 100572044 | R1304: 55572044 | S1304: Profit | T1304: 38250 | U1304: Jay Russell | V1304: 38250 | W1304: September | X1304: Monday | Y1304: 2004 | Z1304: 20
A1305: tt0349825 | B1305: Miracle | C1305: Miracle | D1305: 0 | E1305: 135 | F1305: 2 | G1305: 15 | H1305: Long Movie | I1305: Biography | J1305: Drama | K1305: History | L1305: 7.4 | M1305: Superhit | N1305: 57540 | O1305: Low | P1305: 28000000 | Q1305: 64445708 | R1305: 36445708 | S1305: Profit | T1305: 38019 | U1305: Gavin O'Connor | V1305: 38019 | W1305: February | X1305: Monday | Y1305: 2004 | Z1305: 2
A1306: tt0349903 | B1306: Ocean's Twelve | C1306: Ocean's Twelve | D1306: 0 | E1306: 125 | F1306: 2 | G1306: 5 | H1306: Long Movie | I1306: Crime | J1306: Thriller | K1306: Unknown | L1306: 6.5 | M1306: Hit | N1306: 407294 | O1306: Median | P1306: 110000000 | Q1306: 362744280 | R1306: 252744280 | S1306: Profit | T1306: 38329 | U1306: Steven Soderbergh | V1306: 38329 | W1306: December | X1306: Wednesday | Y1306: 2004 | Z1306: 8
A1307: tt0350258 | B1307: Ray | C1307: Ray | D1307: 0 | E1307: 152 | F1307: 2 | G1307: 32 | H1307: Long Movie | I1307: Biography | J1307: Drama | K1307: Music | L1307: 7.7 | M1307: Superhit | N1307: 154876 | O1307: Median | P1307: 40000000 | Q1307: 123971376 | R1307: 83971376 | S1307: Profit | T1307: 38242 | U1307: Taylor Hackford | V1307: 38242 | W1307: September | X1307: Sunday | Y1307: 2004 | Z1307: 12
A1308: tt0351283 | B1308: Madagascar | C1308: Madagascar | D1308: 0 | E1308: 86 | F1308: 1 | G1308: 26 | H1308: TV Movie | I1308: Adventure | J1308: Animation | K1308: Comedy | L1308: 6.9 | M1308: Hit | N1308: 426684 | O1308: Median | P1308: 75000000 | Q1308: 542063846 | R1308: 467063846 | S1308: Profit | T1308: 38497 | U1308: Eric Darnell, Tom McGrath | V1308: 38497 | W1308: May | X1308: Wednesday | Y1308: 2005 | Z1308: 25
A1309: tt0351977 | B1309: Walking Tall | C1309: Walking Tall | D1309: 0 | E1309: 86 | F1309: 1 | G1309: 26 | H1309: TV Movie | I1309: Action | J1309: Crime | K1309: Unknown | L1309: 6.3 | M1309: Hit | N1309: 108947 | O1309: Median | P1309: 46000000 | Q1309: 57223890 | R1309: 11223890 | S1309: Profit | T1309: 38075 | U1309: Kevin Bray | V1309: 38075 | W1309: March | X1309: Monday | Y1309: 2004 | Z1309: 29
A1310: tt0352248 | B1310: Cinderella Man | C1310: Cinderella Man | D1310: 0 | E1310: 144 | F1310: 2 | G1310: 24 | H1310: Long Movie | I1310: Biography | J1310: Drama | K1310: Romance | L1310: 8 | M1310: Superhit | N1310: 195114 | O1310: Median | P1310: 88000000 | Q1310: 108539911 | R1310: 20539911 | S1310: Profit | T1310: 38495 | U1310: Ron Howard | V1310: 38495 | W1310: May | X1310: Monday | Y1310: 2005 | Z1310: 23
A1311: tt0353969 | B1311: Memories of Murder | C1311: Salinui chueok | D1311: 0 | E1311: 131 | F1311: 2 | G1311: 11 | H1311: Long Movie | I1311: Crime | J1311: Drama | K1311: Mystery | L1311: 8.1 | M1311: Superhit | N1311: 206029 | O1311: Median | P1311: 2800000 | Q1311: 1204841 | R1311: -1595159 | S1311: Loss | T1311: 37743 | U1311: Bong Joon Ho | V1311: 37743 | W1311: May | X1311: Friday | Y1311: 2003 | Z1311: 2
A1312: tt0354899 | B1312: The Science of Sleep | C1312: La science des rÃªves | D1312: 0 | E1312: 105 | F1312: 1 | G1312: 45 | H1312: TV Movie | I1312: Comedy | J1312: Drama | K1312: Fantasy | L1312: 7.2 | M1312: Superhit | N1312: 70458 | O1312: Low | P1312: 6000000 | Q1312: 15116179 | R1312: 9116179 | S1312: Profit | T1312: 38759 | U1312: Michel Gondry | V1312: 38759 | W1312: February | X1312: Saturday | Y1312: 2006 | Z1312: 11
... A1527: tt0416320 | B1527: Match Point | C1527: Match Point | D1527: 0 | E1527: 124 | F1527: 2 | G1527: 4 | H1527: Long Movie | I1527: Drama | J1527: Romance | K1527: Thriller | L1527: 7.6 | M1527: Superhit | N1527: 225226 | O1527: Median | P1527: 15000000 | Q1527: 85638656 | R1527: 70638656 | S1527: Profit | T1527: 38484 | U1527: Woody Allen | V1527: 38484 | W1527: May | X1527: Thursday | Y1527: 2005 | Z1527: 12
A1528: tt0416449 | B1528: 300 | C1528: 300 | D1528: 0 | E1528: 117 | F1528: 1 | G1528: 57 | H1528: TV Movie | I1528: Action | J1528: Drama | K1528: Unknown | L1528: 7.6 | M1528: Superhit | N1528: 849600 | O1528: High | P1528: 65000000 | Q1528: 456082343 | R1528: 391082343 | S1528: Profit | T1528: 39060 | U1528: Zack Snyder | V1528: 39060 | W1528: December | X1528: Saturday | Y1528: 2006 | Z1528: 9
A1529: tt0416508 | B1529: Becoming Jane | C1529: Becoming Jane | D1529: 0 | E1529: 120 | F1529: 2 | G1529: 0 | H1529: TV Movie | I1529: Biography | J1529: Drama | K1529: Romance | L1529: 7 | M1529: Hit | N1529: 64262 | O1529: Low | P1529: 16500000 | Q1529: 37311672 | R1529: 20811672 | S1529: Profit | T1529: 39143 | U1529: Julian Jarrold | V1529: 39143 | W1529: March | X1529: Friday | Y1529: 2007 | Z1529: 2
A1530: tt0417148 | B1530: Snakes on a Plane | C1530: Snakes on a Plane | D1530: 0 | E1530: 105 | F1530: 1 | G1530: 45 | H1530: TV Movie | I1530: Action | J1530: Adventure | K1530: Crime | L1530: 5.5 | M1530: Hit | N1530: 143393 | O1530: Median | P1530: 33000000 | Q1530: 62022014 | R1530: 29022014 | S1530: Profit | T1530: 38946 | U1530: David R. Ellis | V1530: 38946 | W1530: August | X1530: Thursday | Y1530: 2006 | Z1530: 17
A1531: tt0417741 | B1531: Harry Potter and the Half-Blood Prince | C1531: Harry Potter and the Half-Blood Prince | D1531: 0 | E1531: 153 | F1531: 2 | G1531: 33 | H1531: Long Movie | I1531: Action | J1531: Adventure | K1531: Family | L1531: 7.6 | M1531: Superhit | N1531: 578478 | O1531: High | P1531: 250000000 | Q1531: 934770304 | R1531: 684770304 | S1531: Profit | T1531: 40000 | U1531: David Yates | V1531: 40000 | W1531: July | X1531: Monday | Y1531: 2009 | Z1531: 6
A1532: tt0418279 | B1532: Transformers | C1532: Transformers | D1532: 0 | E1532: 144 | F1532: 2 | G1532: 24 | H1532: Long Movie | I1532: Action | J1532: Adventure | K1532: Sci-Fi | L1532: 7 | M1532: Hit | N1532: 665305 | O1532: High | P1532: 150000000 | Q1532: 709709780 | R1532: 559709780 | S1532: Profit | T1532: 39245 | U1532: Michael Bay | V1532: 39245 | W1532: June | X1532: Tuesday | Y1532: 2007 | Z1532: 12
A1533: tt0418689 | B1533: Flags of Our Fathers | C1533: Flags of Our Fathers | D1533: 0 | E1533: 135 | F1533: 2 | G1533: 15 | H1533: Long Movie | I1533: Action | J1533: Adventure | K1533: Drama | L1533: 7.1 | M1533: Superhit | N1533: 127723 | O1533: Median | P1533: 90000000 | Q1533: 65900249 | R1533: -24099751 | S1533: Loss | T1533: 38999 | U1533: Clint Eastwood | V1533: 38999 | W1533: October | X1533: Monday | Y1533: 2006 | Z1533: 9
A1534: tt0418763 | B1534: Jarhead | C1534: Jarhead | D1534: 0 | E1534: 125 | F1534: 2 | G1534: 5 | H1534: Long Movie | I1534: Biography | J1534: Drama | K1534: War | L1534: 7 | M1534: Hit | N1534: 202062 | O1534: Median | P1534: 72000000 | Q1534: 97076152 | R1534: 25076152 | S1534: Profit | T1534: 38652 | U1534: Sam Mendes | V1534: 38652 | W1534: October | X1534: Thursday | Y1534: 2005 | Z1534: 27
A1535: tt0418819 | B1535: Land of the Dead | C1535: Land of the Dead | D1535: 0 | E1535: 93 | F1535: 1 | G1535: 33 | H1535: TV Movie | I1535: Horror | J1535: Sci-Fi | K1535: Thriller | L1535: 6.2 | M1535: Hit | N1535: 99717 | O1535: Low | P1535: 15000000 | Q1535: 47074133 | R1535: 32074133 | S1535: Profit | T1535: 38521 | U1535: George A. Romero | V1535: 38521 | W1535: June | X1535: Saturday | Y1535: 2005 | Z1535: 18
A1536: tt0419706 | B1536: Doom | C1536: Doom | D1536: 0 | E1536: 105 | F1536: 1 | G1536: 45 | H1536: TV Movie | I1536: Action | J1536: Horror | K1536: Sci-Fi | L1536: 5.2 | M1536: Hit | N1536: 117478 | O1536: Median | P1536: 60000000 | Q1536: 58072119 | R1536: -1927881 | S1536: Loss | T1536: 38645 | U1536: Andrzej Bartkowiak | V1536: 38645 | W1536: October | X1536: Thursday | Y1536: 2005 | Z1536: 20
A1537: tt0419887 | B1537: The Kite Runner | C1537: The Kite Runner | D1537: 0 | E1537: 128 | F1537: 2 | G1537: 8 | H1537: Long Movie | I1537: Drama | J1537: Unknown | K1537: Unknown | L1537: 7.6 | M1537: Superhit | N1537: 81924 | O1537: Low | P1537: 20000000 | Q1537: 75011029 | R1537: 55011029 | S1537: Profit | T1537: 39356 | U1537: Marc Forster | V1537: 39356 | W1537: October | X1537: Monday | Y1537: 2007 | Z1537: 1
A1538: tt0420223 | B1538: Stranger Than Fiction | C1538: Stranger Than Fiction | D1538: 0 | E1538: 113 | F1538: 1 | G1538: 53 | H1538: TV Movie | I1538: Comedy | J1538: Drama | K1538: Fantasy | L1538: 7.5 | M1538: Superhit | N1538: 234573 | O1538: Median | P1538: 30000000 | Q1538: 53653224 | R1538: 23653224 | S1538: Profit | T1538: 38969 | U1538: Marc Forster | V1538: 38969 | W1538: September | X1538: Saturday | Y1538: 2006 | Z1538: 9
A1539: tt0420294 | B1539: The Texas Chainsaw Massacre: The Beginning | C1539: The Texas Chainsaw Massacre: The Beginning | D1539: 0 | E1539: 91 | F1539: 1 | G1539: 31 | H1539: TV Movie | I1539: Horror | J1539: Unknown | K1539: Unknown | L1539: 5.8 | M1539: Hit | N1539: 76364 | O1539: Low | P1539: 16000000 | Q1539: 51764406 | R1539: 35764406 | S1539: Profit | T1539: 38995 | U1539: Jonathan Liebesman | V1539: 38995 | W1539: October | X1539: Thursday | Y1539: 2006 | Z1539: 5
A1540: tt0420332 | B1540: Veer-Zaara | C1540: Veer-Zaara | D1540: 0 | E1540: 192 | F1540: 3 | G1540: 12 | H1540: Long Movie | I1540: Drama | J1540: Family | K1540: Musical | L1540: 7.8 | M1540: Superhit | N1540: 56015 | O1540: Low | P1540: 7000000 | Q1540: 6887221 | R1540: -112779 | S1540: Loss | T1540: 38303 | U1540: Yash Chopra | V1540: 38303 | W1540: November | X1540: Friday | Y1540: 2004 | Z1540: 12
... A1627: tt0450345 | B1627: The Wicker Man | C1627: The Wicker Man | D1627: 0 | E1627: 102 | F1627: 1 | G1627: 42 | H1627: TV Movie | I1627: Horror | J1627: Mystery | K1627: Thriller | L1627: 3.8 | M1627: Average | N1627: 70515 | O1627: Low | P1627: 40000000 | Q1627: 38805380 | R1627: -1194620 | S1627: Loss | T1627: 38960 | U1627: Neil LaBute | V1627: 38960 | W1627: August | X1627: Thursday | Y1627: 2006 | Z1627: 31
A1628: tt0450385 | B1628: 1408 | C1628: 1408 | D1628: 0 | E1628: 104 | F1628: 1 | G1628: 44 | H1628: TV Movie | I1628: Fantasy | J1628: Horror | K1628: Mystery | L1628: 6.8 | M1628: Hit | N1628: 288018 | O1628: Median | P1628: 25000000 | Q1628: 132963417 | R1628: 107963417 | S1628: Profit | T1628: 39245 | U1628: Mikael HÃ¥fstrÃ¶m | V1628: 39245 | W1628: June | X1628: Tuesday | Y1628: 2007 | Z1628: 12
A1629: tt0451079 | B1629: Horton Hears a Who! | C1629: Horton Hears a Who! | D1629: 0 | E1629: 86 | F1629: 1 | G1629: 26 | H1629: TV Movie | I1629: Adventure | J1629: Animation | K1629: Comedy | L1629: 6.8 | M1629: Hit | N1629: 147958 | O1629: Median | P1629: 85000000 | Q1629: 298572799 | R1629: 213572799 | S1629: Profit | T1629: 39510 | U1629: Jimmy Hayward, Steve Martino | V1629: 39510 | W1629: March | X1629: Monday | Y1629: 2008 | Z1629: 3
...

Sheet EDA
A1: KPI1
B2: TOTAL MOVIES
A3: Count of id
A4: 3348 | B4: =GETPIVOTDATA("id",$A$3) -> 3348
A7: KPI2 | B7: AVERAGE RATING
A9: Average of averageRating
A10: 6.7385305 | B10: =GETPIVOTDATA("averageRating",$A$9) -> 6.7385305
A12: KPI3 | B12: TOTAL BUDGET
A14: Sum of budget
A15: 168715109116 | B15: =GETPIVOTDATA("budget",$A$14) -> 168715109116
A18: KPI4 | B18: TOTAL GROSS REVENUE
A20: Sum of gross
A21: 554423191764 | B21: =GETPIVOTDATA("gross",$A$20) -> 554423191764
A24: KPI5 | B24: TOTAL PROFIT
A26: Sum of Profit
A27: 385708082648 | B27: =GETPIVOTDATA("Profit",$A$26) -> 385708082648
A29: KPI6 | B29: TOTAL DIRECTORES
A31: Count of directors
A32: 3348 | B32: =GETPIVOTDATA("directors",$A$31) -> 3348
A34: KPI7 | B34: HIGHEST RATED MOVIE
B36: Column Labels
B37: Average | C37: BlockBuster | D37: Flop | E37: Hit | F37: Superhit | G37: Grand Total
A38: Count of id | B38: 99 | C38: 2 | D38: 3 | E38: 1954 | F38: 1290 | G38: 3348
B39: =GETPIVOTDATA("id",$A$36,"Movie Type","Average") -> 99 | C39: =GETPIVOTDATA("id",$A$36,"Movie Type","BlockBuster") -> 2 | D39: =GETPIVOTDATA("id",$A$36,"Movie Type","Flop") -> 3 | E39: =GETPIVOTDATA("id",$A$36,"Movie Type","Hit") -> 1954 | F39: =GETPIVOTDATA("id",$A$36,"Movie Type","Superhit") -> 1290 | G39: =GETPIVOTDATA("id",$A$36) -> 3348
A41: KPI8 | B41: HIGHEST GROSSING MOVIE
A43: Max of gross
A44: 2923706026 | B44: =GETPIVOTDATA("gross",$A$43) -> 2923706026
A46: KPI9 | B46: HIGHEST PROFIT MOVIE
A48: Max of Profit
A49: 2686706026 | B49: =GETPIVOTDATA("Profit",$A$48) -> 2686706026
A51: KPI10 | B51: AVERAGE VOTES
A54: Average of numVotes
A55: 215549.24 | B55: =GETPIVOTDATA("numVotes",$A$54) -> 215549.24
A58: EDA 1 | B58: MOVIES RELEASED IN YEAR
A60: Count of id
A61: 3348
A73: EDA2 | B73: MONTH OF THE HIGHEST MOVIE RELEASED
A75: Row Labels | B75: Count of originalTitle
A76: September | B76: 424
A77: June | B77: 358
A78: May | B78: 342
A79: December | B79: 338
A80: July | B80: 286
A81: January | B81: 257
A82: March | B82: 256
A83: August | B83: 237
A84: November | B84: 236
A85: October | B85: 227
A86: February | B86: 193
A87: April | B87: 189
... A89: Grand Total | B89: 3348
A92: EDA3 | B92: MOST MOVIE RELEASED IN A DAY
A94: Row Labels | B94: Count of originalTitle
A95: Friday | B95: 716
A96: Thursday | B96: 613
A97: Wednesday | B97: 558
A98: Monday | B98: 459
A99: Tuesday | B99: 378
A100: Saturday | B100: 327
A101: Sunday | B101: 292
A102: NA | B102: 5
A103: Grand Total | B103: 3348
A104: EDA4 | B104: PRIMARY GENRE
A106: Row Labels | B106: Count of originalTitle
A107: Action | B107: 1171
A108: Comedy | B108: 701
A109: Drama | B109: 474
A110: Adventure | B110: 345
A111: Crime | B111: 219
A112: Grand Total | B112: 2910
A117: EDA5 | B117: SECOND GENRE
A119: Row Labels | B119: Count of originalTitle
A120: Drama | B120: 748
A121: Adventure | B121: 550
A122: Crime | B122: 323
A123: Comedy | B123: 261
A124: Mystery | B124: 224
A125: Grand Total | B125: 2106
A130: EDA6 | B130: DIRECTOR DIRECTED MOST MOVIES
A132: Row Labels | B132: Count of originalTitle
A133: Steven Spielberg | B133: 30
A134: Ridley Scott | B134: 23
A135: Martin Scorsese | B135: 21
A136: Clint Eastwood | B136: 20
A137: Ron Howard | B137: 19
A138: Tim Burton | B138: 18
A139: Robert Zemeckis | B139: 16
A140: Michael Bay | B140: 15
A141: Tony Scott | B141: 14
A142: Woody Allen | B142: 14
A143: Steven Soderbergh | B143: 14
A144: Grand Total | B144: 204
A147: EDA7 | B147: DIRECTORS WITH HIGHEST MOVIE RATING
A149: Row Labels | B149: Average of averageRating
A150: George Roy Hill | B150: 8.3
A151: Isao Takahata | B151: 8.5
A152: John Lasseter | B152: 8.3
A153: Kemp Powers, Joaquim Dos Santos, Justin K. Thompson | B153: 8.7
A154: Lee Unkrich | B154: 8.3
A155: Lee Unkrich, Adrian Molina | B155: 8.4
...

Sheet Dashboard
A1: TOATL MOVIES | C1: AVERAGE RATING | F1: IMDB DASHBOARD | R1: TOTAL REVENUE | U1: TOTAL PROFIT
A2: =EDA!B4 -> 3348 | C2: =EDA!B10 -> 6.7385305 | R2: =EDA!B21 -> 554423191764 | U2: =EDA!B27 -> 385708082648
J3: AVERAGE VOTES
J4: =EDA!B55 -> 215549.24
